Workbook

Sheet Hướng dẫn
A1: Phiếu chấm T3 — Phân tích lỗi
A3: Người chấm | B3: Người chấm B
A4: Họ tên
A5: Ngày hoàn thành
A7: Mục đích | B7: Kiểm tra nhãn lỗi do máy gán tự động cho các câu mô hình trả lời sai, và chọn ví dụ minh họa cho bài báo.
A8: Cách làm | B8: Mỗi dòng là một câu mô hình trả lời sai. Đọc câu hỏi, evidence (nếu có), schema mô hình nhận được, SQL mô hình sinh và SQL tham chiếu. Sau đó điền các ô màu vàng ở sheet "Lỗi".
A9: Ô cần điền | B9: Nhãn lỗi đúng (chọn trong danh sách) · Câu hỏi/SQL tham chiếu có vấn đề? · Dùng làm ví dụ trong bài? · Ghi chú. Cột "Nhãn tự động đúng?" tự tính, không cần điền.
A10: Chọn nhãn | B10: Chọn nguyên nhân chính khiến kết quả sai. Nếu có nhiều lỗi, chọn lỗi xuất hiện sớm nhất theo thứ tự danh mục dưới đây.
A12: Danh mục nhãn
A13: SQL không chạy được | B13: SQL bị lỗi cú pháp, dùng bảng/cột không tồn tại, hoặc chạy quá thời gian. Phiếu này chỉ gồm các SQL chạy được, nên nhãn này hiếm khi dùng.
A14: Thiếu bảng cần thiết trong schema | B14: Schema mô hình nhận được thiếu một bảng mà câu trả lời đúng cần dùng (do bước lọc schema bỏ mất).
A15: Chọn sai bảng | B15: Schema có đủ bảng nhưng mô hình dùng sai bảng hoặc thiếu/thừa bảng.
A16: Sai cột | B16: Đúng bảng nhưng chọn sai cột (trong SELECT, JOIN hoặc điều kiện).
A17: Sai hàm gộp hoặc GROUP BY | B17: Sai COUNT/SUM/AVG/MIN/MAX hoặc sai GROUP BY.
A18: Sai điều kiện hoặc giá trị | B18: Sai điều kiện WHERE/HAVING: sai toán tử, sai giá trị hằng, thiếu/thừa điều kiện.
A19: Sai sắp xếp hoặc LIMIT | B19: Sai ORDER BY, chiều sắp xếp hoặc LIMIT.
A20: Khác | B20: Lỗi khác: DISTINCT, điều kiện JOIN, định dạng giá trị, hoặc SQL tham chiếu có vấn đề.
A22: Nhóm | B22: A: ViBIRD, model 7B — baseline đúng nhưng full sai (xem SQL của full). B: ViSpider, model 0.5B — full đúng nhưng baseline sai (xem SQL của baseline). C: sai ở cả năm config, model 7B (xem SQL của full).
A23: Lưu ý | B23: Không trao đổi với người chấm còn lại trong khi chấm. Thời gian dự kiến khoảng 3 giờ.
A25: Ví dụ một dòng đã chấm
A26: Câu hỏi | B26: Có bao nhiêu ca sĩ đến từ Pháp?
A27: SQL mô hình sinh | B27: SELECT COUNT(*) FROM singer WHERE Country = 'Pháp'
A28: SQL tham chiếu | B28: SELECT count(*) FROM singer WHERE country = 'France'
A29: Nhãn tự động | B29: Sai điều kiện hoặc giá trị
A30: Nhãn lỗi đúng | B30: Sai điều kiện hoặc giá trị
A31: Câu hỏi/SQL tham chiếu có vấn đề? | B31: Không
A32: Dùng làm ví dụ trong bài? | B32: Có
A33: Ghi chú | B33: Mô hình dịch giá trị sang tiếng Việt thay vì giữ giá trị trong database

Sheet Lỗi
A1: STT | B1: Nhóm | C1: Dataset | D1: Model / config | E1: Câu hỏi | F1: Evidence | G1: Schema mô hình nhận được | H1: SQL mô hình sinh | I1: SQL tham chiếu | J1: Trạng thái thực thi | K1: Nhãn tự động | L1: Nhãn lỗi đúng | M1: Nhãn tự động đúng? | N1: Câu hỏi/SQL tham chiếu có vấn đề? | O1: Dùng làm ví dụ trong bài? | P1: Ghi chú
A2: 1 | B2: A | C2: ViBIRD | D2: Qwen2.5-Coder-7B / full | E2: Địa chỉ đầy đủ của trường có tỷ lệ xuất sắc thấp nhất là gì? Hãy cho biết Street, City, Zip và State. | F2: Tỷ lệ xuất sắc = NumGE1500 / NumTstTakr; địa chỉ đầy đủ có Street, City, State, Zip code | G2: Table: satscores (Kết quả kỳ thi SAT) - cds TEXT | alias: Mã trung tâm, Mã học viện, Mã cơ sở giáo dục | values: 01100170000000, 01100170109835, 01100170112607 | -- Mã duy nhất của trung tâm hoặc cơ sở giáo dục. - dname TEXT | alias: Tên đơn vị hành chính, Tên quận, Tên thành phố | values: Alameda County Office of Education, Alameda Unified, Albany City Unified | -- Tên đơn vị hành chính nơi trường hoặc học viện nằm. Table: schools (Các trường học) - CDSCode TEXT | alias: Mã CDS, Mã trường, Mã định danh | values: 01100170000000, 01100170109835, 01100170112607 | -- Mã định danh duy nhất của trường học. - Street TEXT | alias: Địa chỉ, Địa chỉ trường, Địa điểm | values: 313 West Winton Avenue, 39899 Balentine Drive, Suite 335, 1515 Webster Street | -- Địa chỉ cụ thể của trường học. - StreetAbr TEXT | alias: Địa chỉ ngắn gọn, Địa chỉ rút gọn, Địa chỉ tắt | values: 313 West Winton Ave., 39899 Balentine Dr., Ste. 335, 1515 Webster St. | -- Địa chỉ của trường học được viết tắt hoặc rút gọn. - City TEXT | alias: Thành phố, Thành phố, Thành phố học | values: Hayward, Newark, Oakland | -- Tên thành phố nơi trường học nằm. - Zip TEXT | alias: Mã bưu chính, Mã ZIP, Mã bưu điện | values: 94544-1136, 94560-5359, 94612-3355 | -- Mã bưu chính của địa chỉ trường học. - MailStreet TEXT | alias: Địa chỉ thư từ, Địa chỉ gửi thư, Địa chỉ nhận thư | values: 313 West Winton Avenue, 39899 Balentine Drive, Suite 335, 1515 Webster Street | -- Địa chỉ cụ thể để gửi thư cho trường học. - MailStrAbr TEXT | alias: Tóm tắt địa chỉ thư từ, Địa chỉ ngắn gọn, Địa chỉ thu gọn | values: 313 West Winton Ave., 39899 Balentine Dr., Ste. 335, 1515 Webster St. | -- Địa chỉ ngắn gọn của trường học được sử dụng trong thư từ. - MailCity TEXT | alias: Thành phố, Thành phố nằm ở, Thành phố đặt trụ sở | values: Hayward, Newark, Oakland | -- Thành phố nơi trường học có trụ sở. - MailZip TEXT | alias: Mã bưu chính, Mã ZIP, Mã bưu điện | values: 94544-1136, 94560-5359, 94612 | -- Mã bưu chính của địa chỉ thư từ của trường học. - MailState TEXT | alias: Tỉnh/Thành phố, Tỉnh, Thành phố | values: CA | -- Tỉnh hoặc thành phố nơi trường học nằm. Foreign keys: satscores.cds = schools.CDSCode | H2: SELECT Street, City, Zip, MailState FROM schools JOIN satscores ON schools.CDSCode = satscores.cds WHERE Street IS NOT NULL AND City IS NOT NULL AND MailState IS NOT NULL AND Zip IS NOT NULL ORDER BY (NumGE1500 / NumTstTakr) ASC LIMIT 1; | I2: SELECT T2.Street, T2.City, T2.State, T2.Zip FROM satscores AS T1 INNER JOIN schools AS T2 ON T1.cds = T2.CDSCode ORDER BY CAST(T1.NumGE1500 AS REAL) / T1.NumTstTakr ASC LIMIT 1 | J2: ok | K2: Sai cột | M2: =IF(L2="","",IF(L2=K2,"Có","Không"))
A3: 2 | B3: A | C3: ViBIRD | D3: Qwen2.5-Coder-7B / full | E3: Điểm viết trung bình của từng trường do Ricci Ulrich quản lý là bao nhiêu? Hãy liệt kê các trường và điểm viết trung bình tương ứng. | F3: Thường thì các nhà quản lý phụ trách các công việc của trường. | G3: Table: satscores (Kết quả kỳ thi SAT) - cds TEXT | alias: Mã trung tâm, Mã học viện, Mã cơ sở giáo dục | values: 01100170000000, 01100170109835, 01100170112607 | -- Mã duy nhất của trung tâm hoặc cơ sở giáo dục. - sname TEXT | alias: Tên trường, Tên học viện, Tên trường học | values: FAME Public Charter, Envision Academy for Arts & Technology, Aspire California College Preparatory Academy | -- Tên của trường hoặc học viện tham gia kỳ thi SAT. - AvgScrRead INTEGER | alias: Điểm trung bình môn đọc hiểu, Điểm môn đọc, Điểm môn hiểu văn | values: 418, 503, 397 | -- Điểm trung bình của thí sinh trong phần đọc hiểu của kỳ thi SAT. - AvgScrMath INTEGER | alias: Điểm trung bình môn toán, Điểm môn toán, Điểm môn giải tích | values: 418, 546, 387 | -- Điểm trung bình của thí sinh trong phần toán của kỳ thi SAT. - AvgScrWrite INTEGER | alias: Điểm trung bình môn viết, Điểm môn viết, Điểm môn ngữ pháp | values: 417, 505, 395 | -- Điểm trung bình của thí sinh trong phần viết của kỳ thi SAT. Table: schools (Các trường học) - CDSCode TEXT | alias: Mã CDS, Mã trường, Mã định danh | values: 01100170000000, 01100170109835, 01100170112607 | -- Mã định danh duy nhất của trường học. - District TEXT | alias: Huyện, Huyện quản lý, Huyện giáo dục | values: Alameda County Office of Education, California School for the Blind (State Special Schl), California School for the Deaf-Fremont (State Special Schl) | -- Tên huyện hoặc đơn vị quản lý giáo dục của trường học. - School TEXT | alias: Tên trường, Tên trường học, Tên trường | values: FAME Public Charter, Envision Academy for Arts & Technology, Aspire California College Preparatory Academy | -- Tên đầy đủ của trường học. - Charter INTEGER | alias: Trường công lập, Trường công, Trường nhà nước | values: 1, 0 | -- Biểu thị trường học là trường công lập (1) hay tư thục (0). - EILCode TEXT | alias: Mã EIL, Mã tổ chức, Mã EIL | values: ELEMHIGH, HS, ELEM | -- Mã tổ chức giáo dục của trường. - LastUpdate DATE | alias: Ngày cập nhật, Ngày sửa đổi, Ngày cập nhật thông tin | values: 2015-06-23, 2015-09-01, 2015-06-18 | -- Ngày cuối cùng thông tin về trường học được cập nhật. Foreign keys: satscores.cds = schools.CDSCode | H3: SELECT s.School, ss.AvgScrWrite FROM satscores ss JOIN schools s ON ss.cds = s.CDSCode WHERE s.School LIKE '%Ricci Ulrich%'; | I3: SELECT T2.School, T1.AvgScrWrite FROM satscores AS T1 INNER JOIN schools AS T2 ON T1.cds = T2.CDSCode WHERE T2.AdmFName1 = 'Ricci' AND T2.AdmLName1 = 'Ulrich' | J3: ok | K3: Sai cột | M3: =IF(L3="","",IF(L3=K3,"Có","Không"))
A4: 3 | B4: A | C4: ViBIRD | D4: Qwen2.5-Coder-7B / full | E4: Vùng của khách hàng có id 3541 là gì? | F4: A3 tham chiếu tới region | G4: Table: client (Khách hàng) - client_id INTEGER | alias: Mã khách hàng, ID khách hàng, Số khách hàng | values: 1, 2, 3 | -- Mã duy nhất để xác định mỗi khách hàng - gender TEXT | alias: Giới tính, Phái, Giới tính khách hàng | values: F, M | -- Giới tính của khách hàng (nam hoặc nữ) - birth_date DATE | alias: Ngày sinh, Ngày sinh nhật, Ngày ra đời | values: 1970-12-13, 1945-02-04, 1940-10-09 | -- Ngày sinh của khách hàng - district_id INTEGER | alias: Mã quận, ID quận, Mã khu vực | values: 18, 1, 5 | -- Mã duy nhất để xác định quận của khách hàng Table: disp (Dữ liệu phân phối) - disp_id INTEGER | alias: Mã phân phối, ID phân phối, Mã DP | values: 1, 2, 3 | -- Mã duy nhất để xác định mỗi bản ghi phân phối. - client_id INTEGER | alias: Mã khách hàng, ID khách hàng, Mã KH | values: 1, 2, 3 | -- Mã duy nhất để xác định mỗi khách hàng trong hệ thống. - account_id INTEGER | alias: Mã tài khoản, ID tài khoản, Mã TK | values: 1, 2, 3 | -- Mã duy nhất để xác định mỗi tài khoản trong hệ thống. Table: district (Quận_Huyện) - district_id INTEGER | alias: Mã_Quận, Mã_QH, ID_Quận | values: 1, 2, 3 | -- Mã duy nhất xác định mỗi quận hoặc huyện. - A4 TEXT | alias: Mã_Tỉnh_Quận, Mã_Tỉnh, Mã_Khu_Vực | values: 1204953, 88884, 75232 | -- Mã số duy nhất xác định tỉnh hoặc khu vực. - A14 INTEGER | alias: Số nguyên, Số nguyên tố, Số nguyên | values: 167, 132, 111 | -- Giá trị số nguyên được ghi nhận trong quận. Table: order (Dữ liệu đơn hàng) - order_id INTEGER | alias: Mã đơn hàng, ID đơn hàng, Số đơn hàng | values: 29401, 29402, 29403 | -- Mã duy nhất để xác định mỗi đơn hàng - account_id INTEGER | alias: Mã tài khoản, ID tài khoản, Số tài khoản | values: 1, 2, 3 | -- Mã duy nhất để xác định mỗi tài khoản khách hàng - account_to INTEGER | alias: Tài khoản nhận, Số tài khoản nhận, Tài khoản đến | values: 87144583, 89597016, 13943797 | -- Số tài khoản nơi nhận tiền Foreign keys: client.district_id = district.district_id disp.client_id = client.client_id disp.account_id = account.account_id order.account_id = account.account_id | H4: SELECT T2.A4 FROM client AS T1 JOIN district AS T2 ON T1.district_id = T2.district_id WHERE T1.client_id = 3541; | I4: SELECT T1.A3 FROM district AS T1 INNER JOIN client AS T2 ON T1.district_id = T2.district_id WHERE T2.client_id = 3541 | J4: ok | K4: Sai cột | M4: =IF(L4="","",IF(L4=K4,"Có","Không"))
A5: 4 | B5: A | C5: ViBIRD | D5: Qwen2.5-Coder-7B / full | E5: Tần suất tài khoản số 3 yêu cầu phát hành báo cáo tài khoản là bao nhiêu? Mục đích ghi nợ tổng cộng 3539 là gì? | F5: k_symbol tham chiếu đến mục đích thanh toán | G5: Table: disp (Dữ liệu phân phối) - disp_id INTEGER | alias: Mã phân phối, ID phân phối, Mã DP | values: 1, 2, 3 | -- Mã duy nhất để xác định mỗi bản ghi phân phối. - client_id INTEGER | alias: Mã khách hàng, ID khách hàng, Mã KH | values: 1, 2, 3 | -- Mã duy nhất để xác định mỗi khách hàng trong hệ thống. - account_id INTEGER | alias: Mã tài khoản, ID tài khoản, Mã TK | values: 1, 2, 3 | -- Mã duy nhất để xác định mỗi tài khoản trong hệ thống. Table: loan (Hóa đơn vay) - loan_id INTEGER | alias: Mã hóa đơn vay, Mã vay, ID vay | values: 4959, 4961, 4962 | -- Mã duy nhất để xác định mỗi hóa đơn vay. - account_id INTEGER | alias: Mã tài khoản, ID tài khoản, Số tài khoản | values: 2, 19, 25 | -- Mã duy nhất để xác định mỗi tài khoản khách hàng. - amount INTEGER | alias: Số tiền vay, Tổng số tiền, Số tiền | values: 80952, 30276, 318480 | -- Số tiền mà khách hàng đã vay theo hóa đơn vay. - payments REAL | alias: Số tiền mỗi kỳ thanh toán, Tiền thanh toán, Số tiền mỗi lần | values: 3373.0, 2523.0, 5308.0 | -- Số tiền cần thanh toán mỗi kỳ theo hóa đơn vay. Table: order (Dữ liệu đơn hàng) - order_id INTEGER | alias: Mã đơn hàng, ID đơn hàng, Số đơn hàng | values: 29401, 29402, 29403 | -- Mã duy nhất để xác định mỗi đơn hàng - account_id INTEGER | alias: Mã tài khoản, ID tài khoản, Số tài khoản | values: 1, 2, 3 | -- Mã duy nhất để xác định mỗi tài khoản khách hàng - account_to INTEGER | alias: Tài khoản nhận, Số tài khoản nhận, Tài khoản đến | values: 87144583, 89597016, 13943797 | -- Số tài khoản nơi nhận tiền - amount REAL | alias: Số tiền, Số tiền giao dịch, Số tiền chuyển | values: 2452.0, 3372.7, 7266.0 | -- Số tiền được chuyển trong mỗi giao dịch Table: trans (Giao Dich) - trans_id INTEGER | alias: ID Giao Dich, Mã Giao Dịch, Số Giao Dịch | values: 1, 5, 6 | -- Mã duy nhất để xác định mỗi giao dịch. - account_id INTEGER | alias: ID Tài Khoản, Mã Tài Khoản, Số Tài Khoản | values: 1, 2, 3 | -- Mã duy nhất để xác định tài khoản liên quan đến giao dịch. - balance INTEGER | alias: Số dư, Dư Số, Số Dư Tài Khoản | values: 1000, 4679, 20977 | -- Số dư tài khoản sau khi thực hiện giao dịch. - account INTEGER | alias: Số Tài Khoản, Mã Tài Khoản, Tài Khoản Giao Dịch | values: 41403269, 87144583, 66487163 | -- Số tài khoản liên quan đến giao dịch. Foreign keys: disp.client_id = client.client_id disp.account_id = account.account_id loan.account_id = account.account_id order.account_id = account.account_id trans.account_id = account.account_id | H5: SELECT COUNT(*) AS frequency FROM trans WHERE account_id = 3 AND k_symbol = 'FIRMS'; | I5: SELECT T1.frequency, T2.k_symbol FROM account AS T1 INNER JOIN (SELECT account_id, k_symbol, SUM(amount) AS total_amount FROM `order` GROUP BY account_id, k_symbol) AS T2 ON T1.account_id = T2.account_id WHERE T1.account_id = 3 AND T2.total_amount = 3539 | J5: ok | K5: Thiếu bảng cần thiết trong schema | M5: =IF(L5="","",IF(L5=K5,"Có","Không"))
A6: 5 | B6: A | C6: ViBIRD | D6: Qwen2.5-Coder-7B / full | E6: Có bao nhiêu tài khoản ở Beroun được mở sau năm 1996? | F6: (no evidence) | G6: Table: account (Tài_Khoản) - account_id INTEGER | alias: Mã_Tài_Khoản, ID_Tài_Khoản, Số_Tài_Khoản | values: 1, 2, 3 | -- Mã duy nhất để xác định tài khoản. - district_id INTEGER | alias: Mã_Huyện, ID_Huyện, Số_Huyện | values: 18, 1, 5 | -- Mã duy nhất để xác định huyện liên quan đến tài khoản. Table: loan (Hóa đơn vay) - loan_id INTEGER | alias: Mã hóa đơn vay, Mã vay, ID vay | values: 4959, 4961, 4962 | -- Mã duy nhất để xác định mỗi hóa đơn vay. - account_id INTEGER | alias: Mã tài khoản, ID tài khoản, Số tài khoản | values: 2, 19, 25 | -- Mã duy nhất để xác định mỗi tài khoản khách hàng. - amount INTEGER | alias: Số tiền vay, Tổng số tiền, Số tiền | values: 80952, 30276, 318480 | -- Số tiền mà khách hàng đã vay theo hóa đơn vay. Table: order (Dữ liệu đơn hàng) - order_id INTEGER | alias: Mã đơn hàng, ID đơn hàng, Số đơn hàng | values: 29401, 29402, 29403 | -- Mã duy nhất để xác định mỗi đơn hàng - account_id INTEGER | alias: Mã tài khoản, ID tài khoản, Số tài khoản | values: 1, 2, 3 | -- Mã duy nhất để xác định mỗi tài khoản khách hàng - bank_to TEXT | alias: Ngân hàng nhận, Ngân hàng đến, Ngân hàng nhận tiền | values: YZ, ST, QR | -- Tên hoặc mã ngân hàng nơi nhận tiền - account_to INTEGER | alias: Tài khoản nhận, Số tài khoản nhận, Tài khoản đến | values: 87144583, 89597016, 13943797 | -- Số tài khoản nơi nhận tiền - amount REAL | alias: Số tiền, Số tiền giao dịch, Số tiền chuyển | values: 2452.0, 3372.7, 7266.0 | -- Số tiền được chuyển trong mỗi giao dịch Table: trans (Giao Dich) - trans_id INTEGER | alias: ID Giao Dich, Mã Giao Dịch, Số Giao Dịch | values: 1, 5, 6 | -- Mã duy nhất để xác định mỗi giao dịch. - account_id INTEGER | alias: ID Tài Khoản, Mã Tài Khoản, Số Tài Khoản | values: 1, 2, 3 | -- Mã duy nhất để xác định tài khoản liên quan đến giao dịch. - balance INTEGER | alias: Số dư, Dư Số, Số Dư Tài Khoản | values: 1000, 4679, 20977 | -- Số dư tài khoản sau khi thực hiện giao dịch. - account INTEGER | alias: Số Tài Khoản, Mã Tài Khoản, Tài Khoản Giao Dịch | values: 41403269, 87144583, 66487163 | -- Số tài khoản liên quan đến giao dịch. Foreign keys: account.district_id = district.district_id loan.account_id = account.account_id order.account_id = account.account_id trans.account_id = account.account_id | H6: SELECT COUNT(*) FROM account WHERE district_id = 1 AND account_id > 1996; | I6: SELECT COUNT(account_id) FROM account AS T1 INNER JOIN district AS T2 ON T1.district_id = T2.district_id WHERE STRFTIME('%Y', T1.date) > '1996' AND T2.A2 = 'Beroun' | J6: ok | K6: Thiếu bảng cần thiết trong schema | M6: =IF(L6="","",IF(L6=K6,"Có","Không"))
A7: 6 | B7: A | C7: ViBIRD | D7: Qwen2.5-Coder-7B / full | E7: Những liên kết nào có phosphorus và nitrogen là các nguyên tử của chúng? | F7: có phosphorus là nguyên tử tương ứng với element = 'p'; có nitrogen là nguyên tử tương ứng với element = 'n' | G7: Table: atom (Cơ Sở Nguyên Tử) - atom_id TEXT | alias: Mã Nguyên Tử, Mã Nguyên tử, ID Nguyên tử | values: TR000_1, TR000_2, TR000_3 | -- Mã duy nhất xác định mỗi nguyên tử. - molecule_id TEXT | alias: Mã Mô Phỏng, Mã Mô phỏng, ID Mô phỏng | values: TR000, TR001, TR002 | -- Mã duy nhất xác định mô phỏng phân tử chứa nguyên tử này. - element TEXT | alias: Phân Tích Hóa Học, Phân tích hóa học, Loại nguyên tử | values: cl, c, h | -- Tên hoặc ký hiệu hóa học của nguyên tố trong nguyên tử. Table: bond (Bonds) - bond_id TEXT | alias: MãBond, IDBond, MãBond | values: TR000_1_2, TR000_2_3, TR000_2_4 | -- Mã duy nhất xác định mỗi liên kết hóa học. - molecule_id TEXT | alias: MãChấtHợp, IDChấtHợp, MãPhân tử | values: TR000, TR001, TR002 | -- Mã duy nhất xác định mỗi chất hợp trong phân tích. - bond_type TEXT | alias: LoạiLiênKết, KiểuLiênKết, LoạiBond | values: -, =, # | -- Kiểu của liên kết hóa học giữa các nguyên tử trong phân tử. Table: connected (Bonds_and_Atoms) - atom_id TEXT | alias: Mã_Atom_1, ID_Atom_1, Atom_ID_1 | values: TR000_1, TR000_2, TR000_3 | -- Mã duy nhất của atom đầu tiên trong liên kết hóa học. - atom_id2 TEXT | alias: Mã_Atom_2, ID_Atom_2, Atom_ID_2 | values: TR000_2, TR000_1, TR000_3 | -- Mã duy nhất của atom thứ hai trong liên kết hóa học. - bond_id TEXT | alias: Mã_Liên_Kết, ID_Liên_Kết, Bond_ID | values: TR000_1_2, TR000_2_3, TR000_2_4 | -- Mã duy nhất của liên kết hóa học giữa hai atom. Table: molecule (Bản ghi phân tử) - molecule_id TEXT | alias: Mã phân tử, ID phân tử, Số hiệu phân tử | values: TR000, TR001, TR002 | -- Mã duy nhất để xác định phân tử. - label TEXT | alias: Nhãn, Biến thể, Tâm trạng | values: +, - | -- Biểu thị trạng thái hoặc đặc điểm của phân tử. Foreign keys: atom.molecule_id = molecule.molecule_id bond.molecule_id = molecule.molecule_id connected.atom_id = atom.atom_id connected.atom_id2 = atom.atom_id connected.bond_id = bond.bond_id | H7: SELECT b.bond_id, b.bond_type FROM bond b JOIN connected c ON b.bond_id = c.bond_id JOIN atom a ON c.atom_id = a.atom_id AND a.element = 'p' JOIN atom a2 ON c.atom_id2 = a2.atom_id AND a2.element = 'n'; | I7: SELECT T2.bond_id FROM atom AS T1 INNER JOIN connected AS T2 ON T1.atom_id = T2.atom_id WHERE T2.bond_id IN ( SELECT T3.bond_id FROM connected AS T3 INNER JOIN atom AS T4 ON T3.atom_id = T4.atom_id WHERE T4.element = 'p' ) AND T1.element = 'n' | J7: ok | K7: Chọn sai bảng | M7: =IF(L7="","",IF(L7=K7,"Có","Không"))
A8: 7 | B8: A | C8: ViBIRD | D8: Qwen2.5-Coder-7B / full | E8: Tỷ lệ phần trăm của nguyên tố clo trong các phân tử có liên kết đơn là bao nhiêu? | F8: nguyên tố clo tham chiếu tới element = 'cl'; liên kết đơn tham chiếu tới bond_type = '-'; phần trăm = DIVIDE(SUM(element = 'cl'), COUNT(atom_id)) as percent where bond_type = '-' | G8: Table: atom (Cơ Sở Nguyên Tử) - atom_id TEXT | alias: Mã Nguyên Tử, Mã Nguyên tử, ID Nguyên tử | values: TR000_1, TR000_2, TR000_3 | -- Mã duy nhất xác định mỗi nguyên tử. - molecule_id TEXT | alias: Mã Mô Phỏng, Mã Mô phỏng, ID Mô phỏng | values: TR000, TR001, TR002 | -- Mã duy nhất xác định mô phỏng phân tử chứa nguyên tử này. - element TEXT | alias: Phân Tích Hóa Học, Phân tích hóa học, Loại nguyên tử | values: cl, c, h | -- Tên hoặc ký hiệu hóa học của nguyên tố trong nguyên tử. Table: bond (Bonds) - bond_id TEXT | alias: MãBond, IDBond, MãBond | values: TR000_1_2, TR000_2_3, TR000_2_4 | -- Mã duy nhất xác định mỗi liên kết hóa học. - molecule_id TEXT | alias: MãChấtHợp, IDChấtHợp, MãPhân tử | values: TR000, TR001, TR002 | -- Mã duy nhất xác định mỗi chất hợp trong phân tích. - bond_type TEXT | alias: LoạiLiênKết, KiểuLiênKết, LoạiBond | values: -, =, # | -- Kiểu của liên kết hóa học giữa các nguyên tử trong phân tử. Table: connected (Bonds_and_Atoms) - atom_id TEXT | alias: Mã_Atom_1, ID_Atom_1, Atom_ID_1 | values: TR000_1, TR000_2, TR000_3 | -- Mã duy nhất của atom đầu tiên trong liên kết hóa học. - atom_id2 TEXT | alias: Mã_Atom_2, ID_Atom_2, Atom_ID_2 | values: TR000_2, TR000_1, TR000_3 | -- Mã duy nhất của atom thứ hai trong liên kết hóa học. - bond_id TEXT | alias: Mã_Liên_Kết, ID_Liên_Kết, Bond_ID | values: TR000_1_2, TR000_2_3, TR000_2_4 | -- Mã duy nhất của liên kết hóa học giữa hai atom. Table: molecule (Bản ghi phân tử) - molecule_id TEXT | alias: Mã phân tử, ID phân tử, Số hiệu phân tử | values: TR000, TR001, TR002 | -- Mã duy nhất để xác định phân tử. Foreign keys: atom.molecule_id = molecule.molecule_id bond.molecule_id = molecule.molecule_id connected.atom_id = atom.atom_id connected.atom_id2 = atom.atom_id connected.bond_id = bond.bond_id | H8: SELECT CAST(SUM(CASE WHEN T1.element = 'cl' THEN 1 ELSE 0 END) AS REAL) * 100 / COUNT(T1.atom_id) AS percent FROM atom AS T1 JOIN connected AS T2 ON T1.atom_id = T2.atom_id JOIN bond AS T3 ON T2.bond_id = T3.bond_id WHERE T3.bond_type = '-'; | I8: SELECT CAST(COUNT(CASE WHEN T.element = 'cl' THEN T.atom_id ELSE NULL END) AS REAL) * 100 / COUNT(T.atom_id) FROM ( SELECT T1.atom_id, T1.element FROM atom AS T1 INNER JOIN molecule AS T2 ON T1.molecule_id = T2.molecule_id INNER JOIN bond AS T3 ON T2.molecule_id = T3.molecule_id WHERE T3.bond_type = '-' ) AS T | J8: ok | K8: Chọn sai bảng | M8: =IF(L8="","",IF(L8=K8,"Có","Không"))
A9: 8 | B9: A | C9: ViBIRD | D9: Qwen2.5-Coder-7B / full | E9: Những thẻ bài nào chỉ có sẵn trên giấy và ngôn ngữ tiếng Nhật? | F9: có sẵn trên giấy ám chỉ availability = 'paper'; 'Japanese' là ngôn ngữ; | G9: Table: cards (Thẻ Bài) - id INTEGER | alias: Mã Thẻ, ID, Số Thẻ | values: 41138, 1349, 23810 | -- Mã duy nhất xác định mỗi thẻ bài. - asciiName TEXT | alias: Tên ASCII, Tên ASCII, Tên Đơn Thuần | values: El-Hajjaj, Junun Efreet, Dandan | -- Tên của thẻ bài được viết dưới dạng chữ cái thường. - availability TEXT | alias: Có Mặt Tại, Được Sử Dụng Trên, Có Trong | values: mtgo,paper, paper, arena | -- Nơi thẻ bài có mặt như MTGO, Paper, Arena. - faceName TEXT | alias: Tên_thẻ, Tên, Tiêu_d/Internal | values: Dusk, Dawn, Commit | -- Tên chính thức của thẻ trong game. - isOnlineOnly INTEGER | alias: Chỉ có thể mua online, Chỉ bán trực tuyến, Không có sẵn tại cửa hàng | values: 0, 1 | -- Indicates whether the card can only be purchased online. - mtgjsonV4Id TEXT | alias: ID_MTGJSON_V4, ID_MTGJSON, ID_V4 | values: ad41be73-582f-58ed-abd4-a88c1f616ac3, 9eb2e54c-a12b-5e88-a9c0-d8c84c52d59c, c0de6fd8-367a-50fb-b2f4-2b8fa5aeb7d9 | -- Mã duy nhất trong cơ sở dữ liệu MTGJSON V4. - mtgoFoilId TEXT | alias: ID_Foil_MTGO, ID_Foil, ID_MTGO | values: 27501, 26993, 27473 | -- Mã duy nhất cho phiên bản lấp lánh trong MTGO. - mtgoId TEXT | alias: ID_MTGO, ID_MTGO, Mã_MTGO | values: 27500, 26992, 27472 | -- Mã duy nhất trong hệ thống MTGO. - printings TEXT | alias: In_ấn, In ấn, Bản in | values: 10E,JUD,UMA, 10E,8ED,9ED,DDC,DVD,IMA,INV,JMP,MB1,P02,PS11,PSAL,S99, 10E,8ED,9ED,ODY | -- Danh sách các bộ in ấn mà thẻ bài xuất hiện. - variations TEXT | alias: Phiên bản, Loại, Kiểu | values: b7c19924-b4bf-56fc-aa73-f586e940bd42, 8fd4e2eb-3eb4-50ea-856b-ef638fa47f8a, 6adaf14d-43e3-521a-adf1-960c808e5b1a | -- Danh sách các phiên bản của thẻ bài. | H9: SELECT * FROM cards WHERE availability = 'paper'; | I9: SELECT T1.name FROM cards AS T1 INNER JOIN foreign_data AS T2 ON T1.uuid = T2.uuid WHERE T1.availability = 'paper' AND T2.language = 'Japanese' | J9: ok | K9: Thiếu bảng cần thiết trong schema | M9: =IF(L9="","",IF(L9=K9,"Có","Không"))
A10: 9 | B10: A | C10: ViBIRD | D10: Qwen2.5-Coder-7B / full | E10: Có bao nhiêu thẻ có rarity in trên bản in và có ruling text được in ngày 01/02/2007? | F10: với rarity in trên bản in tương ứng với rarity = 'rare'; ngày 01/02/2007 tương ứng với date = '2007-02-01' | G10: Table: cards (Thẻ Bài) - id INTEGER | alias: Mã Thẻ, ID, Số Thẻ | values: 41138, 1349, 23810 | -- Mã duy nhất xác định mỗi thẻ bài. - hasContentWarning INTEGER | alias: Cảnh_caution, Cảnh_caution, Nội_dung_cảnh_báo | values: 0, 1 | -- Trường hợp có cảnh báo nội dung cho thẻ này. - mtgoId TEXT | alias: ID_MTGO, ID_MTGO, Mã_MTGO | values: 27500, 26992, 27472 | -- Mã duy nhất trong hệ thống MTGO. - name TEXT | alias: Tên, Tên gọi, Tiêu đề | values: Ancestor's Chosen, Angel of Mercy, Aven Cloudchaser | -- Tên của thẻ bài. - originalReleaseDate TEXT | alias: Ngày_ban_hành, Ngày phát hành, Ngày xuất bản | values: 2012/12/1, 2006/12/1, 2007/12/1 | -- Ngày ban hành đầu tiên của thẻ bài. - originalText TEXT | alias: Nội_dung, Nội dung gốc, Phát biểu | values: First strike (This creature deals combat damage before creatures without first strike.) When Ancestor's Chosen comes into play, you gain 1 life for each card in your graveyard., Flying (This creature can't be blocked except by creatures with flying or reach.) When Angel of Mercy comes into play, you gain 3 life., Flying (This creature can't be blocked except by creatures with flying or reach.) When Aven Cloudchaser comes into play, destroy target enchantment. | -- Nội dung hoặc mô tả của thẻ bài. - rarity TEXT | alias: Kỳ_quân, Kỳ hiếm, Loại hiếm | values: uncommon, common, rare | -- Kỳ hiếm của thẻ bài. - text TEXT | alias: Nội_Dung, Chú_Thích, Thông_Tin | values: First strike (This creature deals combat damage before creatures without first strike.) When Ancestor's Chosen enters the battlefield, you gain 1 life for each card in your graveyard., Flying When Angel of Mercy enters the battlefield, you gain 3 life., Flying (This creature can't be blocked except by creatures with flying or reach.) When Aven Cloudchaser enters the battlefield, destroy target enchantment. | -- Nội dung văn bản mô tả năng lực và hiệu ứng của thẻ. - toughness TEXT | alias: Độ_Dẻo_Giòn, Độ_Dẻo, Độ_Giòn | values: 4, 3, 2 | -- Số điểm sức mạnh mà thẻ có thể chịu đựng trước khi bị phá hủy. Table: rulings (Quyết định) - id INTEGER | alias: Mã quyết định, ID, Số quyết định | values: 1, 2, 3 | -- Mã duy nhất để xác định mỗi quyết định. - uuid TEXT | alias: Mã duy nhất, ID duy nhất, UUID | values: 6d268c95-c176-5766-9a46-c14f739aba1c, 56f4935b-f6c5-59b9-88bf-9bcce20247ce, 7fef665c-36a1-5f7a-9299-cf8938708710 | -- Mã duy nhất được sử dụng để xác định bản ghi này trong hệ thống. Foreign keys: rulings.uuid = cards.uuid | H10: SELECT COUNT(cards.id) FROM cards JOIN rulings ON cards.uuid = rulings.uuid WHERE cards.rarity = 'rare' AND rulings.date = '2007-02-01'; | I10: SELECT COUNT(DISTINCT T1.id) FROM cards AS T1 INNER JOIN rulings AS T2 ON T1.uuid = T2.uuid WHERE T1.rarity = 'rare' AND T2.date = '2007-02-01' | J10: ok | K10: Khác | M10: =IF(L10="","",IF(L10=K10,"Có","Không"))
A11: 10 | B11: A | C11: ViBIRD | D11: Qwen2.5-Coder-7B / full | E11: Tên tiếng Ý của bộ bài có "Ancestor's Chosen" nằm trong đó là gì? | F11: Tiếng Ý là một ngôn ngữ tham chiếu tới language = 'Italian'; với "Ancestor's Chosen" trong bộ bài tham chiếu tới name = 'Ancestor''s Chosen' | G11: Table: cards (Thẻ Bài) - id INTEGER | alias: Mã Thẻ, ID, Số Thẻ | values: 41138, 1349, 23810 | -- Mã duy nhất xác định mỗi thẻ bài. - duelDeck TEXT | alias: Kết Hợp Đấu, Kết Hợp, Đấu Kết Hợp | values: a, b | -- Tên của kết hợp đấu mà thẻ bài thuộc về. - faceName TEXT | alias: Tên_thẻ, Tên, Tiêu_d/Internal | values: Dusk, Dawn, Commit | -- Tên chính thức của thẻ trong game. - mtgArenaId TEXT | alias: ID_Arena_MTG, ID_Arena, ID_MTG | values: 74983, 74986, 74987 | -- Mã duy nhất trong hệ thống Arena MTG. - mtgoFoilId TEXT | alias: ID_Foil_MTGO, ID_Foil, ID_MTGO | values: 27501, 26993, 27473 | -- Mã duy nhất cho phiên bản lấp lánh trong MTGO. - mtgoId TEXT | alias: ID_MTGO, ID_MTGO, Mã_MTGO | values: 27500, 26992, 27472 | -- Mã duy nhất trong hệ thống MTGO. - name TEXT | alias: Tên, Tên gọi, Tiêu đề | values: Ancestor's Chosen, Angel of Mercy, Aven Cloudchaser | -- Tên của thẻ bài. - originalReleaseDate TEXT | alias: Ngày_ban_hành, Ngày phát hành, Ngày xuất bản | values: 2012/12/1, 2006/12/1, 2007/12/1 | -- Ngày ban hành đầu tiên của thẻ bài. - originalText TEXT | alias: Nội_dung, Nội dung gốc, Phát biểu | values: First strike (This creature deals combat damage before creatures without first strike.) When Ancestor's Chosen comes into play, you gain 1 life for each card in your graveyard., Flying (This creature can't be blocked except by creatures with flying or reach.) When Angel of Mercy comes into play, you gain 3 life., Flying (This creature can't be blocked except by creatures with flying or reach.) When Aven Cloudchaser comes into play, destroy target enchantment. | -- Nội dung hoặc mô tả của thẻ bài. - originalType TEXT | alias: Loại, Kiểu, Loại thẻ | values: Creature - Human Cleric, Creature - Angel, Creature - Bird Soldier | -- Kiểu hoặc loại của thẻ bài. - side TEXT | alias: Phía, Phía_A, Phía_B | values: a, b, c | -- Phía của thẻ khi nó được sử dụng trong trò chơi. | H11: SELECT T1.duelDeck FROM cards AS T1 JOIN cards AS T2 ON T1.id = T2.mtgoId WHERE T2.name = 'Ancestor''s Chosen'; | I11: SELECT translation FROM set_translations WHERE setCode IN ( SELECT setCode FROM cards WHERE name = 'Ancestor''s Chosen' ) AND language = 'Italian' | J11: ok | K11: Thiếu bảng cần thiết trong schema | M11: =IF(L11="","",IF(L11=K11,"Có","Không"))
A12: 11 | B12: A | C12: ViBIRD | D12: Qwen2.5-Coder-7B / full | E12: Nội dung flavor text bằng tiếng Ý của thẻ bài "Ancestor's Chosen" là gì? | F12: Tiếng Ý tham chiếu tới language = 'Italian'; flavor text tham chiếu tới flavorText; "Ancestor's Chosen" tham chiếu tới name = 'Ancestor''s Chosen' | G12: Table: cards (Thẻ Bài) - id INTEGER | alias: Mã Thẻ, ID, Số Thẻ | values: 41138, 1349, 23810 | -- Mã duy nhất xác định mỗi thẻ bài. - faceName TEXT | alias: Tên_thẻ, Tên, Tiêu_d/Internal | values: Dusk, Dawn, Commit | -- Tên chính thức của thẻ trong game. - flavorName TEXT | alias: Tên_flavor, Tên_flavor, Tên_thêm | values: Godzilla, King of the Monsters, King Caesar, Ancient Guardian, Mothra, Supersonic Queen | -- Tên flavor hoặc tên thay thế cho thẻ. - flavorText TEXT | alias: Nội_dung_flavor, Nội_dung_flavor, Nội_dung_thêm | values: Every tear shed is a drop of immortality., The perfect antidote for a tightly packed formation., Life is measured in inches. To a healer, every one of those inches is precious. | -- Nội dung flavor hoặc thông điệp bổ sung cho thẻ. - hasContentWarning INTEGER | alias: Cảnh_caution, Cảnh_caution, Nội_dung_cảnh_báo | values: 0, 1 | -- Trường hợp có cảnh báo nội dung cho thẻ này. - mtgoFoilId TEXT | alias: ID_Foil_MTGO, ID_Foil, ID_MTGO | values: 27501, 26993, 27473 | -- Mã duy nhất cho phiên bản lấp lánh trong MTGO. - originalReleaseDate TEXT | alias: Ngày_ban_hành, Ngày phát hành, Ngày xuất bản | values: 2012/12/1, 2006/12/1, 2007/12/1 | -- Ngày ban hành đầu tiên của thẻ bài. - originalText TEXT | alias: Nội_dung, Nội dung gốc, Phát biểu | values: First strike (This creature deals combat damage before creatures without first strike.) When Ancestor's Chosen comes into play, you gain 1 life for each card in your graveyard., Flying (This creature can't be blocked except by creatures with flying or reach.) When Angel of Mercy comes into play, you gain 3 life., Flying (This creature can't be blocked except by creatures with flying or reach.) When Aven Cloudchaser comes into play, destroy target enchantment. | -- Nội dung hoặc mô tả của thẻ bài. - side TEXT | alias: Phía, Phía_A, Phía_B | values: a, b, c | -- Phía của thẻ khi nó được sử dụng trong trò chơi. - text TEXT | alias: Nội_Dung, Chú_Thích, Thông_Tin | values: First strike (This creature deals combat damage before creatures without first strike.) When Ancestor's Chosen enters the battlefield, you gain 1 life for each card in your graveyard., Flying When Angel of Mercy enters the battlefield, you gain 3 life., Flying (This creature can't be blocked except by creatures with flying or reach.) When Aven Cloudchaser enters the battlefield, destroy target enchantment. | -- Nội dung văn bản mô tả năng lực và hiệu ứng của thẻ. Table: foreign_data (Dữ liệu nước ngoài) - id INTEGER | alias: Mã ID, Mã, ID | values: 1, 2, 3 | -- Mã duy nhất để xác định mỗi dòng dữ liệu. - flavorText TEXT | alias: Nội dung phong cách, Nội dung, Phong cách | values: „Es ist der Wille aller, und meine Hand, die ihn ausführt.", "La voluntad de todos, realizada por mi mano.", « La volonté de tous passe par ma main. » | -- Nội dung văn bản mang tính chất mô tả hoặc bổ sung cho mục tiêu. - uuid TEXT | alias: Mã UUID, Mã, UUID | values: 5f8287b1-5bb6-5f4c-ad17-316a40d5bb0c, 57aaebc1-850c-503d-9f6e-bb8d00d8bf7c, 8ac972b5-9f6e-5cc8-91c3-b9a40a98232e | -- Mã duy nhất toàn cầu để xác định mỗi đối tượng. Foreign keys: foreign_data.uuid = cards.uuid | H12: SELECT T1.flavorText FROM foreign_data AS T1 JOIN cards AS T2 ON T1.uuid = T2.uuid WHERE T2.faceName = 'Ancestor''s Chosen' AND T1.language = 'Italian'; | I12: SELECT T2.flavorText FROM cards AS T1 INNER JOIN foreign_data AS T2 ON T2.uuid = T1.uuid WHERE T1.name = 'Ancestor''s Chosen' AND T2.language = 'Italian' | J12: ok | K12: Sai cột | M12: =IF(L12="","",IF(L12=K12,"Có","Không"))
A13: 12 | B13: A | C13: ViBIRD | D13: Qwen2.5-Coder-7B / full | E13: Trong số các bài viết do csgillespie sở hữu, có bao nhiêu bài viết là root posts? | F13: "csgillespie" là DisplayName của người dùng; root post tham chiếu tới ParentId IS Null | G13: Table: comments (Bình_luận) - Id INTEGER | alias: Mã_bình_luận, ID, Số_bình_luận | values: 1, 2, 3 | -- Mã duy nhất để xác định mỗi bình luận. - PostId INTEGER | alias: Mã_bài_viết, ID_bài_viết, Số_bài_viết | values: 3, 5, 9 | -- Mã duy nhất để xác định bài viết liên quan đến bình luận này. - UserId INTEGER | alias: Mã_người_dùng, ID_người_dùng, Số_người_dùng | values: 13, 37, 5 | -- Mã duy nhất để xác định người dùng đã tạo bình luận. Table: posts (Bài Viết) - Id INTEGER | alias: Mã Bài Viết, ID, Số Bài Viết | values: 1, 2, 3 | -- Mã duy nhất để xác định mỗi bài viết. - Score INTEGER | alias: Điểm, Điểm Thích, Điểm | values: 23, 22, 54 | -- Số lượt thích hoặc điểm của bài viết. - Body TEXT | alias: Nội Dung, Nội Dung Bài Viết, Chính Văn | values: <p>How should I elicit prior distributions from experts when fitting a Bayesian model?</p> , <p>In many different statistical methods there is an "assumption of normality". What is "normality" and how do I know if there is normality?</p> , <p>What are some valuable Statistical Analysis open source projects available right now?</p> <p>Edit: as pointed out by Sharpie, valuable could mean helping you get things done faster or more cheaply.</p> | -- Nội dung chính của bài viết, thường là câu hỏi hoặc trả lời. - OwnerUserId INTEGER | alias: Mã Người Đăng, Người Đăng, ID Người Đăng | values: 8, 24, 18 | -- Mã người dùng đăng bài viết. - Title TEXT | alias: Tiêu Đề, Tiêu Đề Bài Viết, Tên | values: Eliciting priors from experts, What is normality?, What are some valuable Statistical Analysis open source projects? | -- Tiêu đề của bài viết. - CommentCount INTEGER | alias: Số_lượng_bình_luận, Số_lượng_phản_hồi, Số_lượng_koment | values: 1, 4, 2 | -- Số_lượng bình_luận được đăng trên bài_viết. - FavoriteCount INTEGER | alias: Số_lượng_yêu_thích, Số_lượng_like, Số_lượng_thích | values: 14, 8, 36 | -- Số_lượng người dùng đã đánh dấu bài_viết là yêu_thích. - LastEditorUserId INTEGER | alias: ID_Tài_khoản_sửa_chỉnh_đợt_cuối, ID_sửa_chỉnh_đợt_cuối, ID_tài_khoản_sửa_chỉnh | values: 88, 183, 23 | -- ID của tài_khoản người dùng đã thực hiện sửa_chỉnh đợt cuối cùng. - CommunityOwnedDate DATETIME | alias: Ngày_bài_viết_trở_thành_cộng_dân, Ngày_cộng_dân, Ngày_trở_thành_cộng_dân | values: 2010-07-19 19:13:28.0, 2010-07-19 19:14:43.0, 2010-08-09 13:05:50.0 | -- Ngày khi bài_viết trở thành sở hữu của cộng_dân. - ParentId INTEGER | alias: ID_bài_viết_cháy, ID_bài_viết_mẹ, ID_cháy | values: 3, 7, 6 | -- ID của bài_viết cha hoặc bài_viết gốc nếu bài_viết này là một câu_hỏi con. - OwnerDisplayName TEXT | alias: Tên_họ_chủ_bài_viết, Tên_chủ_bài_viết, Tên_họ_tài_khoản_chủ | values: user28, user209, Michael Bishop | -- Tên_họ của người dùng chủ sở hữu bài_viết. Table: votes (Đánh giá) - Id INTEGER | alias: Mã đánh giá, ID, Mã | values: 1, 2, 3 | -- Mã duy nhất để xác định mỗi bản ghi trong bảng. - PostId INTEGER | alias: Mã bài viết, ID bài viết, Mã bài | values: 3, 2, 5 | -- Mã duy nhất của bài viết được đánh giá. - UserId INTEGER | alias: Mã người dùng, ID người dùng, Mã thành viên | values: 58, 6, 66 | -- Mã duy nhất của người dùng thực hiện đánh giá. Foreign keys: comments.PostId = posts.Id comments.UserId = users.Id posts.OwnerUserId = users.Id posts.LastEditorUserId = users.Id posts.ParentId = posts.Id votes.PostId = posts.Id votes.UserId = users.Id | H13: SELECT COUNT(*) FROM posts WHERE OwnerDisplayName = 'csgillespie' AND ParentId IS NULL; | I13: SELECT COUNT(T1.Id) FROM posts AS T1 INNER JOIN users AS T2 ON T1.OwnerUserId = T2.Id WHERE T2.DisplayName = 'csgillespie' AND T1.ParentId IS NULL | J13: ok | K13: Thiếu bảng cần thiết trong schema | M13: =IF(L13="","",IF(L13=K13,"Có","Không"))
... A41: 40 | B41: A | C41: ViBIRD | D41: Qwen2.5-Coder-7B / full | E41: Loại tiền tệ mà khách hàng thanh toán vào lúc 16:25:00 vào ngày 2012/8/24 là gì? | F41: '2012/8/24' có thể được biểu diễn bằng '2012-08-24'; | G41: Table: customers (Khách hàng) - CustomerID INTEGER | alias: Mã khách hàng, ID khách hàng, Số khách hàng | values: 3, 5, 6 | -- Mã duy nhất xác định mỗi khách hàng - Currency TEXT | alias: Đơn vị tiền tệ, Tiền tệ, ĐVT tiền tệ | values: EUR, CZK | -- Loại tiền tệ được sử dụng trong giao dịch với khách hàng Table: transactions_1k (Giao_dịch_1000) - TransactionID INTEGER | alias: Mã_giao_dịch, Mã giao dịch, ID giao dịch | values: 1, 2, 3 | -- Mã duy nhất để xác định mỗi giao dịch - Date DATE | alias: Ngày, Ngày giao dịch, Ngày thực hiện | values: 2012-08-24, 2012-08-23, 2012-08-25 | -- Ngày thực hiện giao dịch - Time TEXT | alias: Thời_gian, Giờ, Thời điểm | values: 09:41:00, 10:03:00, 13:53:00 | -- Thời gian thực hiện giao dịch - CardID INTEGER | alias: Mã_thẻ, Mã thẻ tín dụng, Mã thẻ ghi nợ | values: 486621, 550134, 684220 | -- Mã thẻ được sử dụng trong giao dịch - GasStationID INTEGER | alias: Mã_phân_xưởng, Mã xăng dầu, Mã phân xưởng | values: 3704, 656, 741 | -- Mã phân xưởng nơi giao dịch được thực hiện - ProductID INTEGER | alias: Mã_sản_phẩm, Mã sản phẩm, ID sản phẩm | values: 2, 23, 5 | -- Mã sản phẩm được mua trong giao dịch - Amount INTEGER | alias: Số_lượng, Số lượng mua, Số lượng sản phẩm | values: 28, 18, 1 | -- Số lượng sản phẩm được mua trong giao dịch - Price REAL | alias: Giá, Giá tiền, Giá bán | values: 672.64, 430.72, 121.99 | -- Giá của sản phẩm trong giao dịch Table: yearmonth (Tháng_Năm) - CustomerID INTEGER | alias: MãKháchHàng, IDKháchHàng, KHID | values: 39, 63, 172 | -- Mã duy nhất xác định khách hàng trong hệ thống. - Date TEXT | alias: NgàyTháng, ThángNăm, Thời Gian | values: 201112, 201201, 201202 | -- Ký hiệu năm tháng (ví dụ: 201112 cho tháng 12 năm 2011). Foreign keys: yearmonth.CustomerID = customers.None | H41: SELECT c.Currency FROM customers c JOIN transactions_1k t ON c.CustomerID = t.CardID WHERE t.Date = '2012-08-24' AND t.Time = '16:25:00'; | I41: SELECT DISTINCT T3.Currency FROM transactions_1k AS T1 INNER JOIN gasstations AS T2 ON T1.GasStationID = T2.GasStationID INNER JOIN customers AS T3 ON T1.CustomerID = T3.CustomerID WHERE T1.Date = '2012-08-24' AND T1.Time = '16:25:00' | J41: ok | K41: Thiếu bảng cần thiết trong schema | M41: =IF(L41="","",IF(L41=K41,"Có","Không"))
A42: 41 | B42: B | C42: ViSpider | D42: Qwen2.5-Coder-0.5B / baseline | E42: Có bao nhiêu chiếc xe có số xi-lanh lớn hơn 4? | G42: Table: car_makers - Id INTEGER - Maker TEXT - FullName TEXT - Country TEXT Table: car_names - MakeId INTEGER - Model TEXT - Make TEXT Table: cars_data - Id INTEGER - MPG TEXT - Cylinders INTEGER - Edispl REAL - Horsepower TEXT - Weight INTEGER - Accelerate REAL - Year INTEGER Table: continents - ContId INTEGER - Continent TEXT Table: countries - CountryId INTEGER - CountryName TEXT - Continent INTEGER Table: model_list - ModelId INTEGER - Maker INTEGER - Model TEXT Foreign keys: car_makers.Country = countries.CountryId car_names.Model = model_list.Model cars_data.Id = car_names.MakeId countries.Continent = continents.ContId model_list.Maker = car_makers.Id | H42: SELECT COUNT(*) FROM cars_data WHERE MPG > 4; | I42: SELECT count(*) FROM CARS_DATA WHERE Cylinders > 4; | J42: ok | K42: Sai cột | M42: =IF(L42="","",IF(L42=K42,"Có","Không"))
A43: 42 | B43: B | C43: ViSpider | D43: Qwen2.5-Coder-0.5B / baseline | E43: Những năm nào đã sản xuất các xe có trọng lượng từ ít nhất 3000 đến nhiều nhất 4000? | G43: Table: car_makers - Id INTEGER - Maker TEXT - FullName TEXT - Country TEXT Table: car_names - MakeId INTEGER - Model TEXT - Make TEXT Table: cars_data - Id INTEGER - MPG TEXT - Cylinders INTEGER - Edispl REAL - Horsepower TEXT - Weight INTEGER - Accelerate REAL - Year INTEGER Table: continents - ContId INTEGER - Continent TEXT Table: countries - CountryId INTEGER - CountryName TEXT - Continent INTEGER Table: model_list - ModelId INTEGER - Maker INTEGER - Model TEXT Foreign keys: car_makers.Country = countries.CountryId car_names.Model = model_list.Model cars_data.Id = car_names.MakeId countries.Continent = continents.ContId model_list.Maker = car_makers.Id | H43: SELECT DISTINCT YEAR FROM cars_data WHERE Horsepower BETWEEN 3000 AND 4000; | I43: select distinct year from cars_data where weight between 3000 and 4000; | J43: ok | K43: Sai cột | M43: =IF(L43="","",IF(L43=K43,"Có","Không"))
A44: 43 | B44: B | C44: ViSpider | D44: Qwen2.5-Coder-0.5B / baseline | E44: Horsepower của chiếc xe có tốc độ tăng tốc cao nhất là bao nhiêu? | G44: Table: car_makers - Id INTEGER - Maker TEXT - FullName TEXT - Country TEXT Table: car_names - MakeId INTEGER - Model TEXT - Make TEXT Table: cars_data - Id INTEGER - MPG TEXT - Cylinders INTEGER - Edispl REAL - Horsepower TEXT - Weight INTEGER - Accelerate REAL - Year INTEGER Table: continents - ContId INTEGER - Continent TEXT Table: countries - CountryId INTEGER - CountryName TEXT - Continent INTEGER Table: model_list - ModelId INTEGER - Maker INTEGER - Model TEXT Foreign keys: car_makers.Country = countries.CountryId car_names.Model = model_list.Model cars_data.Id = car_names.MakeId countries.Continent = continents.ContId model_list.Maker = car_makers.Id | H44: SELECT MAX(Horsepower) FROM cars_data WHERE Accelerate > 0; | I44: SELECT T1.horsepower FROM CARS_DATA AS T1 ORDER BY T1.accelerate DESC LIMIT 1; | J44: ok | K44: Sai hàm gộp hoặc GROUP BY | M44: =IF(L44="","",IF(L44=K44,"Có","Không"))
A45: 44 | B45: B | C45: ViSpider | D45: Qwen2.5-Coder-0.5B / baseline | E45: Horsepower của chiếc xe có tốc độ tăng tốc cao nhất là bao nhiêu? | G45: Table: car_makers - Id INTEGER - Maker TEXT - FullName TEXT - Country TEXT Table: car_names - MakeId INTEGER - Model TEXT - Make TEXT Table: cars_data - Id INTEGER - MPG TEXT - Cylinders INTEGER - Edispl REAL - Horsepower TEXT - Weight INTEGER - Accelerate REAL - Year INTEGER Table: continents - ContId INTEGER - Continent TEXT Table: countries - CountryId INTEGER - CountryName TEXT - Continent INTEGER Table: model_list - ModelId INTEGER - Maker INTEGER - Model TEXT Foreign keys: car_makers.Country = countries.CountryId car_names.Model = model_list.Model cars_data.Id = car_names.MakeId countries.Continent = continents.ContId model_list.Maker = car_makers.Id | H45: SELECT MAX(Horsepower) FROM cars_data WHERE Accelerate > 0; | I45: SELECT T1.horsepower FROM CARS_DATA AS T1 ORDER BY T1.accelerate DESC LIMIT 1; | J45: ok | K45: Sai hàm gộp hoặc GROUP BY | M45: =IF(L45="","",IF(L45=K45,"Có","Không"))
A46: 45 | B46: B | C46: ViSpider | D46: Qwen2.5-Coder-0.5B / baseline | E46: Có bao nhiêu xe có hơn 6 xi lanh? | G46: Table: car_makers - Id INTEGER - Maker TEXT - FullName TEXT - Country TEXT Table: car_names - MakeId INTEGER - Model TEXT - Make TEXT Table: cars_data - Id INTEGER - MPG TEXT - Cylinders INTEGER - Edispl REAL - Horsepower TEXT - Weight INTEGER - Accelerate REAL - Year INTEGER Table: continents - ContId INTEGER - Continent TEXT Table: countries - CountryId INTEGER - CountryName TEXT - Continent INTEGER Table: model_list - ModelId INTEGER - Maker INTEGER - Model TEXT Foreign keys: car_makers.Country = countries.CountryId car_names.Model = model_list.Model cars_data.Id = car_names.MakeId countries.Continent = continents.ContId model_list.Maker = car_makers.Id | H46: SELECT COUNT(*) FROM cars_data WHERE MPG > 6 | I46: SELECT COUNT(*) FROM CARS_DATA WHERE Cylinders > 6; | J46: ok | K46: Sai cột | M46: =IF(L46="","",IF(L46=K46,"Có","Không"))
A47: 46 | B47: B | C47: ViSpider | D47: Qwen2.5-Coder-0.5B / baseline | E47: Airline 'JetBlue Airways' có bao nhiêu chuyến bay? | G47: Table: airlines - uid INTEGER - Airline TEXT - Abbreviation TEXT - Country TEXT Table: airports - City TEXT - AirportCode TEXT - AirportName TEXT - Country TEXT - CountryAbbrev TEXT Table: flights - Airline INTEGER - FlightNo INTEGER - SourceAirport TEXT - DestAirport TEXT Foreign keys: flights.SourceAirport = airports.AirportCode flights.DestAirport = airports.AirportCode | H47: SELECT COUNT(*) FROM flights WHERE Airline = 'JetBlue Airways'; | I47: SELECT count(*) FROM FLIGHTS AS T1 JOIN AIRLINES AS T2 ON T1.Airline = T2.uid WHERE T2.Airline = "JetBlue Airways" | J47: ok | K47: Chọn sai bảng | M47: =IF(L47="","",IF(L47=K47,"Có","Không"))
A48: 47 | B48: B | C48: ViSpider | D48: Qwen2.5-Coder-0.5B / baseline | E48: Những hãng hàng không nào có ít nhất 10 chuyến bay? | G48: Table: airlines - uid INTEGER - Airline TEXT - Abbreviation TEXT - Country TEXT Table: airports - City TEXT - AirportCode TEXT - AirportName TEXT - Country TEXT - CountryAbbrev TEXT Table: flights - Airline INTEGER - FlightNo INTEGER - SourceAirport TEXT - DestAirport TEXT Foreign keys: flights.SourceAirport = airports.AirportCode flights.DestAirport = airports.AirportCode | H48: SELECT DISTINCT T2.Airline FROM airlines AS T1 INNER JOIN flights AS T2 ON T1.uid = T2.Airline GROUP BY T1.Airline HAVING COUNT(T2.FlightNo) < 10; | I48: SELECT T1.Airline FROM AIRLINES AS T1 JOIN FLIGHTS AS T2 ON T1.uid = T2.Airline GROUP BY T1.Airline HAVING count(*) > 10 | J48: ok | K48: Sai cột | M48: =IF(L48="","",IF(L48=K48,"Có","Không"))
A49: 48 | B49: B | C49: ViSpider | D49: Qwen2.5-Coder-0.5B / baseline | E49: Các số hiệu chuyến bay của các chuyến bay khởi hành từ sân bay "APG" là gì? | G49: Table: airlines - uid INTEGER - Airline TEXT - Abbreviation TEXT - Country TEXT Table: airports - City TEXT - AirportCode TEXT - AirportName TEXT - Country TEXT - CountryAbbrev TEXT Table: flights - Airline INTEGER - FlightNo INTEGER - SourceAirport TEXT - DestAirport TEXT Foreign keys: flights.SourceAirport = airports.AirportCode flights.DestAirport = airports.AirportCode | H49: SELECT COUNT(*) FROM flights WHERE SourceAirport = 'APG' | I49: SELECT FlightNo FROM FLIGHTS WHERE SourceAirport = "APG" | J49: ok | K49: Sai cột | M49: =IF(L49="","",IF(L49=K49,"Có","Không"))
A50: 49 | B50: B | C50: ViSpider | D50: Qwen2.5-Coder-0.5B / baseline | E50: Các số hiệu chuyến bay của các chuyến bay đến sân bay "APG" là gì? | G50: Table: airlines - uid INTEGER - Airline TEXT - Abbreviation TEXT - Country TEXT Table: airports - City TEXT - AirportCode TEXT - AirportName TEXT - Country TEXT - CountryAbbrev TEXT Table: flights - Airline INTEGER - FlightNo INTEGER - SourceAirport TEXT - DestAirport TEXT Foreign keys: flights.SourceAirport = airports.AirportCode flights.DestAirport = airports.AirportCode | H50: SELECT COUNT(*) FROM flights WHERE SourceAirport = 'APG' | I50: SELECT FlightNo FROM FLIGHTS WHERE DestAirport = "APG" | J50: ok | K50: Sai cột | M50: =IF(L50="","",IF(L50=K50,"Có","Không"))
A51: 50 | B51: B | C51: ViSpider | D51: Qwen2.5-Coder-0.5B / baseline | E51: Các số hiệu chuyến bay của các chuyến bay khởi hành từ thành phố "Aberdeen" là gì? | G51: Table: airlines - uid INTEGER - Airline TEXT - Abbreviation TEXT - Country TEXT Table: airports - City TEXT - AirportCode TEXT - AirportName TEXT - Country TEXT - CountryAbbrev TEXT Table: flights - Airline INTEGER - FlightNo INTEGER - SourceAirport TEXT - DestAirport TEXT Foreign keys: flights.SourceAirport = airports.AirportCode flights.DestAirport = airports.AirportCode | H51: SELECT COUNT(*) FROM flights WHERE SourceAirport = 'Aberdeen' | I51: SELECT T1.FlightNo FROM FLIGHTS AS T1 JOIN AIRPORTS AS T2 ON T1.SourceAirport = T2.AirportCode WHERE T2.City = "Aberdeen" | J51: ok | K51: Chọn sai bảng | M51: =IF(L51="","",IF(L51=K51,"Có","Không"))
A52: 51 | B52: B | C52: ViSpider | D52: Qwen2.5-Coder-0.5B / baseline | E52: Hãy cho biết các số hiệu chuyến bay khởi hành từ Aberdeen. | G52: Table: airlines - uid INTEGER - Airline TEXT - Abbreviation TEXT - Country TEXT Table: airports - City TEXT - AirportCode TEXT - AirportName TEXT - Country TEXT - CountryAbbrev TEXT Table: flights - Airline INTEGER - FlightNo INTEGER - SourceAirport TEXT - DestAirport TEXT Foreign keys: flights.SourceAirport = airports.AirportCode flights.DestAirport = airports.AirportCode | H52: SELECT COUNT(*) FROM flights WHERE SourceAirport = 'Aberdeen' | I52: SELECT T1.FlightNo FROM FLIGHTS AS T1 JOIN AIRPORTS AS T2 ON T1.SourceAirport = T2.AirportCode WHERE T2.City = "Aberdeen" | J52: ok | K52: Chọn sai bảng | M52: =IF(L52="","",IF(L52=K52,"Có","Không"))
A53: 52 | B53: B | C53: ViSpider | D53: Qwen2.5-Coder-0.5B / baseline | E53: Các số hiệu chuyến bay của các chuyến bay đến thành phố "Aberdeen" là gì? | G53: Table: airlines - uid INTEGER - Airline TEXT - Abbreviation TEXT - Country TEXT Table: airports - City TEXT - AirportCode TEXT - AirportName TEXT - Country TEXT - CountryAbbrev TEXT Table: flights - Airline INTEGER - FlightNo INTEGER - SourceAirport TEXT - DestAirport TEXT Foreign keys: flights.SourceAirport = airports.AirportCode flights.DestAirport = airports.AirportCode | H53: SELECT COUNT(*) FROM flights WHERE DestAirport = 'Aberdeen' | I53: SELECT T1.FlightNo FROM FLIGHTS AS T1 JOIN AIRPORTS AS T2 ON T1.DestAirport = T2.AirportCode WHERE T2.City = "Aberdeen" | J53: ok | K53: Chọn sai bảng | M53: =IF(L53="","",IF(L53=K53,"Có","Không"))
... A101: 100 | B101: C | C101: ViSpider | D101: Qwen2.5-Coder-7B / full | E101: Tên và họ của các chuyên gia đã thực hiện các treatment với cost thấp hơn mức trung bình là gì? | G101: Table: Professionals (Người chuyên nghiệp) - professional_id INTEGER | alias: Mã chuyên viên, ID chuyên viên, Mã nhân viên | values: 1, 2, 3 | -- Mã duy nhất để xác định mỗi chuyên viên. - first_name VARCHAR(50) | alias: Họ, Tên đệm, Tên đầu | values: Taryn, Jayson, Olaf | -- Tên đệm hoặc tên đầu của chuyên viên. - street VARCHAR(50) | alias: Địa chỉ, Địa chỉ đường, Địa chỉ nhà | values: 6915 Oberbrunner Point Suite 491 Gleasonville, LA , 88665 Terence Lodge Apt. 904 Corneliusfort, NC 194, 68589 Bradly Manor New Audrey, IN 91497 | -- Địa chỉ cụ thể của chuyên viên. - last_name VARCHAR(50) | alias: Tên, Tên họ, Tên cuối | values: Braun, Ullrich, Watsica | -- Tên họ của chuyên viên. Table: Treatment_Types (Loại_Chữa_Bệnh) - treatment_type_code VARCHAR(10) | alias: Mã_Loại_Chữa_Bệnh, Mã Loại Chữa Bệnh, Mã Loại Trị Liệu | values: EXAM, VAC, WALK | -- Mã đại diện cho loại hình điều trị. - treatment_type_description VARCHAR(80) | alias: Miêu_Tả_Loại_Chữa_Bệnh, Miêu tả Loại Chữa Bệnh, Miêu tả Loại Trị Liệu | values: Physical examination, Vaccination, Take for a Walk | -- Miêu tả chi tiết về loại hình điều trị. Table: Treatments (Chữa trị) - treatment_id INTEGER | alias: Mã điều trị, ID điều trị, Số điều trị | values: 1, 2, 3 | -- Mã duy nhất để xác định mỗi lần điều trị. - dog_id INTEGER | alias: Mã chó, ID chó, Số chó | values: 14, 4, 2 | -- Mã duy nhất để xác định mỗi con chó được điều trị. - professional_id INTEGER | alias: Mã nhân viên y tế, ID nhân viên, Số nhân viên | values: 9, 10, 4 | -- Mã duy nhất để xác định nhân viên y tế thực hiện điều trị. - treatment_type_code VARCHAR(10) | alias: Loại điều trị, Kiểu điều trị, Phương pháp điều trị | values: WALK, VAC, EXAM | -- Mã đại diện cho loại điều trị được thực hiện cho chó. - date_of_treatment DATETIME | alias: Ngày điều trị, Ngày thực hiện, Ngày khám | values: 2018-03-19 04:39:54, 2018-03-15 20:25:34, 2018-03-08 05:26:23 | -- Ngày khi điều trị được thực hiện cho chó. - cost_of_treatment DECIMAL(19,4) | alias: Chi phí điều trị, Giá trị điều trị, Phí điều trị | values: 567, 147, 429 | -- Chi phí tổng cộng cho dịch vụ điều trị được thực hiện. Foreign keys: Treatments.dog_id = Dogs.dog_id Treatments.professional_id = Professionals.professional_id Treatments.treatment_type_code = Treatment_Types.treatment_type_code | H101: SELECT p.first_name, p.last_name FROM Professionals p JOIN Treatments t ON p.professional_id = t.professional_id WHERE t.cost_of_treatment < (SELECT AVG(cost_of_treatment) FROM Treatments); | I101: SELECT DISTINCT T1.first_name , T1.last_name FROM Professionals AS T1 JOIN Treatments AS T2 WHERE cost_of_treatment < ( SELECT avg(cost_of_treatment) FROM Treatments ) | J101: ok | K101: Sai cột | M101: =IF(L101="","",IF(L101=K101,"Có","Không"))
A102: 101 | B102: C | C102: ViBIRD | D102: Qwen2.5-Coder-7B / full | E102: Xếp hạng các trường theo điểm trung bình môn Writing, với điều kiện điểm lớn hơn 499, đồng thời cho biết số charter của chúng. | F102: Số charter hợp lệ có nghĩa là số không null | G102: Table: satscores (Kết quả kỳ thi SAT) - cds TEXT | alias: Mã trung tâm, Mã học viện, Mã cơ sở giáo dục | values: 01100170000000, 01100170109835, 01100170112607 | -- Mã duy nhất của trung tâm hoặc cơ sở giáo dục. - AvgScrWrite INTEGER | alias: Điểm trung bình môn viết, Điểm môn viết, Điểm môn ngữ pháp | values: 417, 505, 395 | -- Điểm trung bình của thí sinh trong phần viết của kỳ thi SAT. Table: schools (Các trường học) - CDSCode TEXT | alias: Mã CDS, Mã trường, Mã định danh | values: 01100170000000, 01100170109835, 01100170112607 | -- Mã định danh duy nhất của trường học. - School TEXT | alias: Tên trường, Tên trường học, Tên trường | values: FAME Public Charter, Envision Academy for Arts & Technology, Aspire California College Preparatory Academy | -- Tên đầy đủ của trường học. - Phone TEXT | alias: Số điện thoại, Điện thoại, Số liên lạc | values: (510) 887-0152, (510) 596-8901, (510) 686-4131 | -- Số điện thoại chính của trường học. - Ext TEXT | alias: Phần mở rộng, Phần phụ, Phần phụ trợ | values: 130, 1240, 1200 | -- Phần mở rộng số điện thoại nếu có. - Website TEXT | alias: Trang web, Trang mạng, Trang thông tin | values: www.acoe.org, www.envisionacademy.org/, www.aspirepublicschools.org | -- Địa chỉ trang web chính thức của trường học. - Charter INTEGER | alias: Trường công lập, Trường công, Trường nhà nước | values: 1, 0 | -- Biểu thị trường học là trường công lập (1) hay tư thục (0). - CharterNum TEXT | alias: Số chứng nhận, Số cấp phép, Số chứng nhận hoạt động | values: 0728, 0811, 1049 | -- Số chứng nhận hoạt động hoặc cấp phép của trường học. - SOC TEXT | alias: Mã SOC, Mã loại trường, Mã phân loại | values: 65, 66, 60 | -- Mã phân loại loại trường học. - SOCType TEXT | alias: Kiểu mã SOC, Kiểu loại trường, Kiểu phân loại | values: K-12 Schools (Public), High Schools (Public), Elementary Schools (Public) | -- Kiểu mã phân loại loại trường học. - EILCode TEXT | alias: Mã EIL, Mã tổ chức, Mã EIL | values: ELEMHIGH, HS, ELEM | -- Mã tổ chức giáo dục của trường. Foreign keys: satscores.cds = schools.CDSCode | H102: SELECT s.School, ss.AvgScrWrite, COUNT(ss.cds) AS CharterCount FROM satscores ss JOIN schools s ON ss.cds = s.CDSCode WHERE ss.AvgScrWrite > 499 AND s.Charter IS NOT NULL GROUP BY s.School, ss.AvgScrWrite; | I102: SELECT CharterNum, AvgScrWrite, RANK() OVER (ORDER BY AvgScrWrite DESC) AS WritingScoreRank FROM schools AS T1 INNER JOIN satscores AS T2 ON T1.CDSCode = T2.cds WHERE T2.AvgScrWrite > 499 AND CharterNum is not null | J102: ok | K102: Sai cột | M102: =IF(L102="","",IF(L102=K102,"Có","Không"))
A103: 102 | B103: C | C103: ViBIRD | D103: Qwen2.5-Coder-7B / full | E103: Có bao nhiêu thí sinh tham gia kỳ thi tại các trường có địa chỉ thư từ ở Fresno? | F103: (no evidence) | G103: Table: satscores (Kết quả kỳ thi SAT) - cds TEXT | alias: Mã trung tâm, Mã học viện, Mã cơ sở giáo dục | values: 01100170000000, 01100170109835, 01100170112607 | -- Mã duy nhất của trung tâm hoặc cơ sở giáo dục. - sname TEXT | alias: Tên trường, Tên học viện, Tên trường học | values: FAME Public Charter, Envision Academy for Arts & Technology, Aspire California College Preparatory Academy | -- Tên của trường hoặc học viện tham gia kỳ thi SAT. - dname TEXT | alias: Tên đơn vị hành chính, Tên quận, Tên thành phố | values: Alameda County Office of Education, Alameda Unified, Albany City Unified | -- Tên đơn vị hành chính nơi trường hoặc học viện nằm. - NumTstTakr INTEGER | alias: Số lượng thí sinh tham gia kỳ thi, Số thí sinh, Số người dự thi | values: 88, 17, 71 | -- Số lượng thí sinh đã tham gia kỳ thi SAT. - NumGE1500 INTEGER | alias: Số lượng thí sinh đạt ít nhất 1500 điểm, Số thí sinh 1500+, Số người đạt 1500+ | values: 14, 9, 5 | -- Số lượng thí sinh đạt tổng điểm ít nhất 1500 trong kỳ thi SAT. Table: schools (Các trường học) - CDSCode TEXT | alias: Mã CDS, Mã trường, Mã định danh | values: 01100170000000, 01100170109835, 01100170112607 | -- Mã định danh duy nhất của trường học. - Street TEXT | alias: Địa chỉ, Địa chỉ trường, Địa điểm | values: 313 West Winton Avenue, 39899 Balentine Drive, Suite 335, 1515 Webster Street | -- Địa chỉ cụ thể của trường học. - MailStreet TEXT | alias: Địa chỉ thư từ, Địa chỉ gửi thư, Địa chỉ nhận thư | values: 313 West Winton Avenue, 39899 Balentine Drive, Suite 335, 1515 Webster Street | -- Địa chỉ cụ thể để gửi thư cho trường học. - MailStrAbr TEXT | alias: Tóm tắt địa chỉ thư từ, Địa chỉ ngắn gọn, Địa chỉ thu gọn | values: 313 West Winton Ave., 39899 Balentine Dr., Ste. 335, 1515 Webster St. | -- Địa chỉ ngắn gọn của trường học được sử dụng trong thư từ. - MailCity TEXT | alias: Thành phố, Thành phố nằm ở, Thành phố đặt trụ sở | values: Hayward, Newark, Oakland | -- Thành phố nơi trường học có trụ sở. - MailZip TEXT | alias: Mã bưu chính, Mã ZIP, Mã bưu điện | values: 94544-1136, 94560-5359, 94612 | -- Mã bưu chính của địa chỉ thư từ của trường học. - MailState TEXT | alias: Tỉnh/Thành phố, Tỉnh, Thành phố | values: CA | -- Tỉnh hoặc thành phố nơi trường học nằm. Foreign keys: satscores.cds = schools.CDSCode | H103: SELECT SUM(s.NumTstTakr) AS TotalTestTakers FROM satscores s JOIN schools sc ON s.cds = sc.CDSCode WHERE sc.MailCity = 'Fresno'; | I103: SELECT T1.NumTstTakr FROM satscores AS T1 INNER JOIN schools AS T2 ON T1.cds = T2.CDSCode WHERE T2.MailCity = 'Fresno' | J103: ok | K103: Sai hàm gộp hoặc GROUP BY | M103: =IF(L103="","",IF(L103=K103,"Có","Không"))
A104: 103 | B104: C | C104: ViBIRD | D104: Qwen2.5-Coder-7B / full | E104: Molecule TR000 có phải là chất gây ung thư hay không? | F104: label = '+' nghĩa là các phân tử là chất gây ung thư; label = '-' nghĩa là các phân tử không phải là chất gây ung thư | G104: Table: atom (Cơ Sở Nguyên Tử) - atom_id TEXT | alias: Mã Nguyên Tử, Mã Nguyên tử, ID Nguyên tử | values: TR000_1, TR000_2, TR000_3 | -- Mã duy nhất xác định mỗi nguyên tử. - molecule_id TEXT | alias: Mã Mô Phỏng, Mã Mô phỏng, ID Mô phỏng | values: TR000, TR001, TR002 | -- Mã duy nhất xác định mô phỏng phân tử chứa nguyên tử này. - element TEXT | alias: Phân Tích Hóa Học, Phân tích hóa học, Loại nguyên tử | values: cl, c, h | -- Tên hoặc ký hiệu hóa học của nguyên tố trong nguyên tử. Table: bond (Bonds) - bond_id TEXT | alias: MãBond, IDBond, MãBond | values: TR000_1_2, TR000_2_3, TR000_2_4 | -- Mã duy nhất xác định mỗi liên kết hóa học. - molecule_id TEXT | alias: MãChấtHợp, IDChấtHợp, MãPhân tử | values: TR000, TR001, TR002 | -- Mã duy nhất xác định mỗi chất hợp trong phân tích. - bond_type TEXT | alias: LoạiLiênKết, KiểuLiênKết, LoạiBond | values: -, =, # | -- Kiểu của liên kết hóa học giữa các nguyên tử trong phân tử. Table: connected (Bonds_and_Atoms) - atom_id TEXT | alias: Mã_Atom_1, ID_Atom_1, Atom_ID_1 | values: TR000_1, TR000_2, TR000_3 | -- Mã duy nhất của atom đầu tiên trong liên kết hóa học. - atom_id2 TEXT | alias: Mã_Atom_2, ID_Atom_2, Atom_ID_2 | values: TR000_2, TR000_1, TR000_3 | -- Mã duy nhất của atom thứ hai trong liên kết hóa học. - bond_id TEXT | alias: Mã_Liên_Kết, ID_Liên_Kết, Bond_ID | values: TR000_1_2, TR000_2_3, TR000_2_4 | -- Mã duy nhất của liên kết hóa học giữa hai atom. Table: molecule (Bản ghi phân tử) - molecule_id TEXT | alias: Mã phân tử, ID phân tử, Số hiệu phân tử | values: TR000, TR001, TR002 | -- Mã duy nhất để xác định phân tử. - label TEXT | alias: Nhãn, Biến thể, Tâm trạng | values: +, - | -- Biểu thị trạng thái hoặc đặc điểm của phân tử. Foreign keys: atom.molecule_id = molecule.molecule_id bond.molecule_id = molecule.molecule_id connected.atom_id = atom.atom_id connected.atom_id2 = atom.atom_id connected.bond_id = bond.bond_id | H104: SELECT CASE WHEN label = '+' THEN 'Có' ELSE 'Không' END AS is_cancerous FROM molecule WHERE molecule_id = 'TR000'; | I104: SELECT label FROM molecule AS T WHERE T.molecule_id = 'TR000' | J104: ok | K104: Khác | M104: =IF(L104="","",IF(L104=K104,"Có","Không"))
A105: 104 | B105: C | C105: ViBIRD | D105: Qwen2.5-Coder-7B / full | E105: Chi phí mana của các thẻ có layout normal, frameVersion 2003, borderColor màu đen và có sẵn cả ở paper và mtgo là bao nhiêu? | F105: có sẵn ở paper và mtgo ám chỉ availability = 'mtgo,paper'; frameVersion = 2003; borderColor = 'black' | G105: Table: cards (Thẻ Bài) - id INTEGER | alias: Mã Thẻ, ID, Số Thẻ | values: 41138, 1349, 23810 | -- Mã duy nhất xác định mỗi thẻ bài. - availability TEXT | alias: Có Mặt Tại, Được Sử Dụng Trên, Có Trong | values: mtgo,paper, paper, arena | -- Nơi thẻ bài có mặt như MTGO, Paper, Arena. - borderColor TEXT | alias: Màu Rìa, Màu Rìm, Màu Gian | values: black, white, borderless | -- Màu sắc của rìa hoặc viền của thẻ bài. - colorIdentity TEXT | alias: Màu Nhập Thể, Màu Nhập, Màu Nhập Thể | values: W, B, U | -- Mảng màu đại diện cho thẻ bài. - convertedManaCost REAL | alias: Chi Phí Mana Đổi Hợp, Chi Phí Mana, Chi Phí Mana Đổi | values: 7.0, 5.0, 4.0 | -- Chi phí mana tổng hợp của thẻ bài. - faceConvertedManaCost REAL | alias: Chi_phí_mana_hợp_lệ, Chi_phí_mana, Chi_phí_hợp_lệ | values: 4.0, 5.0, 6.0 | -- Chi phí mana hợp lệ của thẻ khi được sử dụng. - frameVersion TEXT | alias: Phiên_bản_khung, Phiên_bản, Khung_thẻ | values: 2003, 1993, 2015 | -- Phiên bản khung của thẻ. - manaCost TEXT | alias: Chi_phí_Mana, Chi_phí, Tốn_man | values: {5}{W}{W}, {4}{W}, {3}{W} | -- Chi phí mana cần thiết để sử dụng thẻ bài. - mtgArenaId TEXT | alias: ID_Arena_MTG, ID_Arena, ID_MTG | values: 74983, 74986, 74987 | -- Mã duy nhất trong hệ thống Arena MTG. - mtgoFoilId TEXT | alias: ID_Foil_MTGO, ID_Foil, ID_MTGO | values: 27501, 26993, 27473 | -- Mã duy nhất cho phiên bản lấp lánh trong MTGO. - mtgoId TEXT | alias: ID_MTGO, ID_MTGO, Mã_MTGO | values: 27500, 26992, 27472 | -- Mã duy nhất trong hệ thống MTGO. | H105: SELECT convertedManaCost FROM cards WHERE availability = 'mtgo,paper' AND frameVersion = '2003' AND borderColor = 'black'; | I105: SELECT manaCost FROM cards WHERE availability = 'mtgo,paper' AND borderColor = 'black' AND frameVersion = 2003 AND layout = 'normal' | J105: ok | K105: Sai cột | M105: =IF(L105="","",IF(L105=K105,"Có","Không"))
A106: 105 | B106: C | C106: ViBIRD | D106: Qwen2.5-Coder-7B / full | E106: Bộ bài thuộc nghệ sĩ nào có văn bản "Das perfekte Gegenmittel zu einer dichten Formation"? | F106: (no evidence) | G106: Table: cards (Thẻ Bài) - id INTEGER | alias: Mã Thẻ, ID, Số Thẻ | values: 41138, 1349, 23810 | -- Mã duy nhất xác định mỗi thẻ bài. - artist TEXT | alias: Tác Giả, Người Hoạ Tác, Nhà Thiết Kế | values: Pete Venters, Volkan Baǵa, Justin Sweet | -- Tên của người hoạ tác hoặc thiết kế thẻ bài. - colorIdentity TEXT | alias: Màu Nhập Thể, Màu Nhập, Màu Nhập Thể | values: W, B, U | -- Mảng màu đại diện cho thẻ bài. - frameVersion TEXT | alias: Phiên_bản_khung, Phiên_bản, Khung_thẻ | values: 2003, 1993, 2015 | -- Phiên bản khung của thẻ. - hasContentWarning INTEGER | alias: Cảnh_caution, Cảnh_caution, Nội_dung_cảnh_báo | values: 0, 1 | -- Trường hợp có cảnh báo nội dung cho thẻ này. - isFullArt INTEGER | alias: Có hình ảnh toàn bộ, Có hình ảnh đầy đủ, Có hình ảnh toàn diện | values: 0, 1 | -- Indicates whether the card has full artwork. - originalText TEXT | alias: Nội_dung, Nội dung gốc, Phát biểu | values: First strike (This creature deals combat damage before creatures without first strike.) When Ancestor's Chosen comes into play, you gain 1 life for each card in your graveyard., Flying (This creature can't be blocked except by creatures with flying or reach.) When Angel of Mercy comes into play, you gain 3 life., Flying (This creature can't be blocked except by creatures with flying or reach.) When Aven Cloudchaser comes into play, destroy target enchantment. | -- Nội dung hoặc mô tả của thẻ bài. - rarity TEXT | alias: Kỳ_quân, Kỳ hiếm, Loại hiếm | values: uncommon, common, rare | -- Kỳ hiếm của thẻ bài. - scryfallIllustrationId TEXT | alias: Mã_Ảnh_Szłay_Forum, Mã_Ảnh, ID_Ảnh | values: be2f7173-c8b7-4172-a388-9b2c6b3c16e5, e4d6c53f-e936-4be8-8b70-47c2be863b20, 2eb663cd-020a-46d8-a6d9-bb63d4b5c848 | -- Mã duy nhất để chỉ định hình ảnh của thẻ trong Szlay Forum. - supertypes TEXT | alias: Loại_Kiểu_Ngoại, Kiểu_Ngoại, Loại_Ngoại | values: Legendary, Basic, Legendary,Snow | -- Kiểu tổng quát của thẻ, nếu có. - text TEXT | alias: Nội_Dung, Chú_Thích, Thông_Tin | values: First strike (This creature deals combat damage before creatures without first strike.) When Ancestor's Chosen enters the battlefield, you gain 1 life for each card in your graveyard., Flying When Angel of Mercy enters the battlefield, you gain 3 life., Flying (This creature can't be blocked except by creatures with flying or reach.) When Aven Cloudchaser enters the battlefield, destroy target enchantment. | -- Nội dung văn bản mô tả năng lực và hiệu ứng của thẻ. | H106: SELECT artist FROM cards WHERE text = 'Das perfekte Gegenmittel zu einer dichten Formation'; | I106: SELECT DISTINCT T1.artist FROM cards AS T1 INNER JOIN foreign_data AS T2 ON T1.uuid = T2.uuid WHERE T2.flavorText LIKE '%DAS perfekte Gegenmittel zu einer dichten Formation%' | J106: ok | K106: Thiếu bảng cần thiết trong schema | M106: =IF(L106="","",IF(L106=K106,"Có","Không"))
A107: 106 | B107: C | C107: ViBIRD | D107: Qwen2.5-Coder-7B / full | E107: Tỷ lệ phần trăm các thẻ có convertedManaCost là 10 trong bộ card Abyssal Horror là bao nhiêu? | F107: bộ card Abyssal Horror tham chiếu tới name = 'Abyssal Horror'; tỷ lệ phần trăm tham chiếu tới DIVIDE(COUNT(convertedManaCost = 16),COUNT(convertedManaCost))*100 | G107: Table: cards (Thẻ Bài) - id INTEGER | alias: Mã Thẻ, ID, Số Thẻ | values: 41138, 1349, 23810 | -- Mã duy nhất xác định mỗi thẻ bài. - colorIdentity TEXT | alias: Màu Nhập Thể, Màu Nhập, Màu Nhập Thể | values: W, B, U | -- Mảng màu đại diện cho thẻ bài. - convertedManaCost REAL | alias: Chi Phí Mana Đổi Hợp, Chi Phí Mana, Chi Phí Mana Đổi | values: 7.0, 5.0, 4.0 | -- Chi phí mana tổng hợp của thẻ bài. - faceConvertedManaCost REAL | alias: Chi_phí_mana_hợp_lệ, Chi_phí_mana, Chi_phí_hợp_lệ | values: 4.0, 5.0, 6.0 | -- Chi phí mana hợp lệ của thẻ khi được sử dụng. - hasAlternativeDeckLimit INTEGER | alias: Có_giới_hạn_deck_thay_thân, Giới_hạn_deck, Deck_thay_thân | values: 0, 1 | -- Trường hợp có giới hạn deck thay thế cho thẻ này. - hasContentWarning INTEGER | alias: Cảnh_caution, Cảnh_caution, Nội_dung_cảnh_báo | values: 0, 1 | -- Trường hợp có cảnh báo nội dung cho thẻ này. - manaCost TEXT | alias: Chi_phí_Mana, Chi_phí, Tốn_man | values: {5}{W}{W}, {4}{W}, {3}{W} | -- Chi phí mana cần thiết để sử dụng thẻ bài. - originalReleaseDate TEXT | alias: Ngày_ban_hành, Ngày phát hành, Ngày xuất bản | values: 2012/12/1, 2006/12/1, 2007/12/1 | -- Ngày ban hành đầu tiên của thẻ bài. - purchaseUrls TEXT | alias: Địa_chỉ_mua_hàng, Địa chỉ mua, Liên kết mua hàng | values: {'cardKingdom': 'https://mtgjson.com/links/9fb51af0ad6f0736', 'cardmarket': 'https://mtgjson.com/links/ace8861194ee0b6a', 'tcgplayer': 'https://mtgjson.com/links/4843cea124a0d515'}, {'cardKingdom': 'https://mtgjson.com/links/027095d094e58f5b', 'cardmarket': 'https://mtgjson.com/links/f6fb5098e1cd1b1e', 'tcgplayer': 'https://mtgjson.com/links/56c4b57293f350ef'}, {'cardKingdom': 'https://mtgjson.com/links/9246105d88032a9f', 'cardmarket': 'https://mtgjson.com/links/dcdfe48e6a8f9e1e', 'tcgplayer': 'https://mtgjson.com/links/3ce595aabe276f80'} | -- Liên kết để mua thẻ bài từ các nhà cung cấp khác nhau. - rarity TEXT | alias: Kỳ_quân, Kỳ hiếm, Loại hiếm | values: uncommon, common, rare | -- Kỳ hiếm của thẻ bài. - side TEXT | alias: Phía, Phía_A, Phía_B | values: a, b, c | -- Phía của thẻ khi nó được sử dụng trong trò chơi. | H107: SELECT CAST(SUM(CASE WHEN convertedManaCost = 10 THEN 1 ELSE 0 END) AS REAL) * 100 / COUNT(*) FROM cards WHERE name = 'Abyssal Horror'; | I107: SELECT CAST(SUM(CASE WHEN T1.convertedManaCost = 10 THEN 1 ELSE 0 END) AS REAL) * 100 / COUNT(T1.id), T1.name FROM cards AS T1 INNER JOIN sets AS T2 ON T2.code = T1.setCode WHERE T1.name = 'Abyssal Horror' | J107: ok | K107: Thiếu bảng cần thiết trong schema | M107: =IF(L107="","",IF(L107=K107,"Có","Không"))
A108: 107 | B108: C | C108: ViBIRD | D108: Qwen2.5-Coder-7B / full | E108: Bộ bài có tên Adarkar Valkyrie chỉ có sẵn ở ngoài Hoa Kỳ không? | F108: bộ bài Adarkar Valkyrie tham chiếu tới name = 'Adarkar Valkyrie'; isForeignOnly = 1 có nghĩa là chỉ có sẵn ở ngoài Hoa Kỳ; | G108: Table: cards (Thẻ Bài) - id INTEGER | alias: Mã Thẻ, ID, Số Thẻ | values: 41138, 1349, 23810 | -- Mã duy nhất xác định mỗi thẻ bài. - availability TEXT | alias: Có Mặt Tại, Được Sử Dụng Trên, Có Trong | values: mtgo,paper, paper, arena | -- Nơi thẻ bài có mặt như MTGO, Paper, Arena. - faceName TEXT | alias: Tên_thẻ, Tên, Tiêu_d/Internal | values: Dusk, Dawn, Commit | -- Tên chính thức của thẻ trong game. - hasAlternativeDeckLimit INTEGER | alias: Có_giới_hạn_deck_thay_thân, Giới_hạn_deck, Deck_thay_thân | values: 0, 1 | -- Trường hợp có giới hạn deck thay thế cho thẻ này. - isOnlineOnly INTEGER | alias: Chỉ có thể mua online, Chỉ bán trực tuyến, Không có sẵn tại cửa hàng | values: 0, 1 | -- Indicates whether the card can only be purchased online. - mtgArenaId TEXT | alias: ID_Arena_MTG, ID_Arena, ID_MTG | values: 74983, 74986, 74987 | -- Mã duy nhất trong hệ thống Arena MTG. - mtgoFoilId TEXT | alias: ID_Foil_MTGO, ID_Foil, ID_MTGO | values: 27501, 26993, 27473 | -- Mã duy nhất cho phiên bản lấp lánh trong MTGO. - mtgoId TEXT | alias: ID_MTGO, ID_MTGO, Mã_MTGO | values: 27500, 26992, 27472 | -- Mã duy nhất trong hệ thống MTGO. - multiverseId TEXT | alias: ID_Multiverse, ID_Multiverse, Mã_Multiverse | values: 130550, 129465, 129470 | -- Mã duy nhất trong vũ trụ Magic: The Gathering. - originalReleaseDate TEXT | alias: Ngày_ban_hành, Ngày phát hành, Ngày xuất bản | values: 2012/12/1, 2006/12/1, 2007/12/1 | -- Ngày ban hành đầu tiên của thẻ bài. - rarity TEXT | alias: Kỳ_quân, Kỳ hiếm, Loại hiếm | values: uncommon, common, rare | -- Kỳ hiếm của thẻ bài. | H108: SELECT CASE WHEN COUNT(*) > 0 THEN 'Có' ELSE 'Không' END AS Result FROM cards WHERE faceName = 'Adarkar Valkyrie' AND isOnlineOnly = 1; | I108: SELECT IIF(isForeignOnly = 1, 'YES', 'NO') FROM cards AS T1 INNER JOIN sets AS T2 ON T2.code = T1.setCode WHERE T1.name = 'Adarkar Valkyrie' | J108: ok | K108: Thiếu bảng cần thiết trong schema | M108: =IF(L108="","",IF(L108=K108,"Có","Không"))
A109: 108 | B109: C | C109: ViBIRD | D109: Qwen2.5-Coder-7B / full | E109: Tiêu đề của bài đăng có liên kết bài đăng lâu đời nhất là gì? | F109: liên kết bài đăng lâu đời nhất tham chiếu tới MIN(CreaionDate); | G109: Table: postHistory (Lịch Sử Bài Viết) - Id INTEGER | alias: Mã, Số ID, ID | values: 1, 2, 3 | -- Mã duy nhất để xác định mỗi bản ghi trong bảng. - PostId INTEGER | alias: Mã Bài Viết, ID Bài Viết, Bài Viết | values: 1, 2, 3 | -- Mã duy nhất để xác định bài viết liên quan đến bản ghi này. - UserId INTEGER | alias: Mã Người Dùng, ID Người Dùng, Người Dùng | values: 8, 24, 18 | -- Mã duy nhất để xác định người dùng đã tạo hoặc cập nhật bản ghi này. Table: postLinks (Liên Kết Bài Viết) - Id INTEGER | alias: Mã Liên Kết, ID, Mã Liên Kết Bài Viết | values: 108, 145, 217 | -- Mã duy nhất để xác định mỗi liên kết bài viết. - CreationDate DATETIME | alias: Ngày Tạo, Ngày Tạo Liên Kết, Ngày Tạo Bài Viết Liên Kết | values: 2010-07-21 14:47:33.0, 2010-07-23 16:30:41.0, 2010-07-26 20:12:15.0 | -- Ngày và thời gian khi liên kết bài viết được tạo. - PostId INTEGER | alias: Mã Bài Viết, ID Bài Viết, Mã Bài Viết Liên Kết | values: 395, 548, 375 | -- Mã duy nhất của bài viết nguồn trong liên kết. - RelatedPostId INTEGER | alias: Mã Bài Viết Liên Quan, ID Bài Viết Liên Quan, Mã Bài Viết Mục Tiêu | values: 173, 539, 30 | -- Mã duy nhất của bài viết liên quan trong liên kết. Table: posts (Bài Viết) - Id INTEGER | alias: Mã Bài Viết, ID, Số Bài Viết | values: 1, 2, 3 | -- Mã duy nhất để xác định mỗi bài viết. - OwnerUserId INTEGER | alias: Mã Người Đăng, Người Đăng, ID Người Đăng | values: 8, 24, 18 | -- Mã người dùng đăng bài viết. - Title TEXT | alias: Tiêu Đề, Tiêu Đề Bài Viết, Tên | values: Eliciting priors from experts, What is normality?, What are some valuable Statistical Analysis open source projects? | -- Tiêu đề của bài viết. - Tags TEXT | alias: Nhãn, Nhãn Bài Viết, Danh Mục | values: <bayesian><prior><elicitation>, <distributions><normality>, <software><open-source> | -- Những từ khóa hoặc nhãn liên quan đến nội dung của bài viết. - LastEditorUserId INTEGER | alias: ID_Tài_khoản_sửa_chỉnh_đợt_cuối, ID_sửa_chỉnh_đợt_cuối, ID_tài_khoản_sửa_chỉnh | values: 88, 183, 23 | -- ID của tài_khoản người dùng đã thực hiện sửa_chỉnh đợt cuối cùng. - LastEditDate DATETIME | alias: Ngày_sửa_chỉnh_đợt_cuối, Ngày_sửa_chỉnh, Ngày_sửa_chỉnh_cuối | values: 2010-08-07 17:56:44.0, 2011-02-12 05:50:03.0, 2010-07-19 19:21:15.0 | -- Ngày và giờ khi bài_viết được sửa_chỉnh lần cuối. - ParentId INTEGER | alias: ID_bài_viết_cháy, ID_bài_viết_mẹ, ID_cháy | values: 3, 7, 6 | -- ID của bài_viết cha hoặc bài_viết gốc nếu bài_viết này là một câu_hỏi con. Table: tags (Nhãn) - Id INTEGER | alias: Mã, Số hiệu, ID | values: 1, 2, 3 | -- Mã duy nhất xác định mỗi nhãn. - ExcerptPostId INTEGER | alias: ID Bài Viết Tóm Tắt, ID Bài Trích, ID Bài Viết Khái Quát | values: 20258, 62158, 67815 | -- ID của bài viết tóm tắt liên quan đến nhãn này. Table: votes (Đánh giá) - Id INTEGER | alias: Mã đánh giá, ID, Mã | values: 1, 2, 3 | -- Mã duy nhất để xác định mỗi bản ghi trong bảng. - PostId INTEGER | alias: Mã bài viết, ID bài viết, Mã bài | values: 3, 2, 5 | -- Mã duy nhất của bài viết được đánh giá. - UserId INTEGER | alias: Mã người dùng, ID người dùng, Mã thành viên | values: 58, 6, 66 | -- Mã duy nhất của người dùng thực hiện đánh giá. Foreign keys: postHistory.PostId = posts.Id postHistory.UserId = users.Id postLinks.PostId = posts.Id postLinks.RelatedPostId = posts.Id posts.OwnerUserId = users.Id posts.LastEditorUserId = users.Id posts.ParentId = posts.Id tags.ExcerptPostId = posts.Id votes.PostId = posts.Id votes.UserId = users.Id | H109: SELECT p.Title FROM posts p JOIN postLinks pl ON p.Id = pl.PostId ORDER BY pl.CreationDate ASC LIMIT 1; | I109: SELECT T1.Title FROM posts AS T1 INNER JOIN postLinks AS T2 ON T2.PostId = T1.Id ORDER BY T1.CreaionDate LIMIT 1 | J109: ok | K109: Sai cột | M109: =IF(L109="","",IF(L109=K109,"Có","Không"))
A110: 109 | B110: C | C110: ViBIRD | D110: Qwen2.5-Coder-7B / full | E110: Trung bình số siêu anh hùng không có màu da là bao nhiêu? | F110: trung bình = DIVIDE(COUNT(superhero.id), SUM(skin_colour_id = 1)); không có màu da tham chiếu tới skin_colour_id WHERE colour.id = 1; | G110: Table: superhero (Anh Hùng Siêu Nhiên) - id INTEGER | alias: Mã ID, ID, Số ID | values: 1, 2, 3 | -- Mã duy nhất để xác định mỗi anh hùng siêu nhiên. - superhero_name TEXT | alias: Tên Anh Hùng Siêu Nhiên, Tên Siêu Anh Hùng, Tên Anh Hùng | values: 3-D Man, A-Bomb, Abe Sapien | -- Tên gọi của anh hùng siêu nhiên trong truyện tranh hoặc phim ảnh. - full_name TEXT | alias: Họ và Tên, Tên Thật, Tên Đầy Đủ | values: Charles Chandler, Richard Milhouse Jones, Abraham Sapien | -- Tên đầy đủ của nhân vật trong thế giới thực. - gender_id INTEGER | alias: Giới Tính, Giới Tính Nam/Nữ, Phái | values: 1, 2, 3 | -- Giới tính của nhân vật được chỉ định bằng số ID. - eye_colour_id INTEGER | alias: Màu Mắt, Màu Nhìn, Màu Môi | values: 9, 33, 7 | -- Màu sắc của mắt nhân vật được chỉ định bằng số ID. - hair_colour_id INTEGER | alias: Màu Tóc, Màu Đầu, Màu Tóc | values: 13, 1, 4 | -- Màu sắc của tóc nhân vật được chỉ định bằng số ID. - skin_colour_id INTEGER | alias: Màu Da, Màu Da, Màu Nước | values: 1, 7, 23 | -- Màu sắc của da nhân vật được chỉ định bằng số ID. - race_id INTEGER | alias: Dân Tộc, Dân Tộc, Loài | values: 1, 24, 33 | -- Dân tộc hoặc loài của nhân vật được chỉ định bằng số ID. - publisher_id INTEGER | alias: Nhà Xuất Bản, Nhà Sáng Tạo, Nhà Sản Xuất | values: 13, 3, 4 | -- Nhà xuất bản hoặc nhà sản xuất truyện tranh của nhân vật được chỉ định bằng số ID. - alignment_id INTEGER | alias: Tư Tưởng, Tư Tưởng, Đạo Đức | values: 1, 2, 3 | -- Tư tưởng hoặc đạo đức của nhân vật được chỉ định bằng số ID. Foreign keys: superhero.gender_id = gender.id superhero.eye_colour_id = colour.id superhero.hair_colour_id = colour.id superhero.skin_colour_id = colour.id superhero.race_id = race.id superhero.publisher_id = publisher.id superhero.alignment_id = alignment.id | H110: SELECT AVG(CASE WHEN skin_colour_id = 1 THEN 1 ELSE 0 END) AS average_no_skin_color FROM superhero; | I110: SELECT CAST(COUNT(*) AS REAL) / SUM(CASE WHEN T2.id = 1 THEN 1 ELSE 0 END) FROM superhero AS T1 INNER JOIN colour AS T2 ON T1.skin_colour_id = T2.id | J110: ok | K110: Thiếu bảng cần thiết trong schema | M110: =IF(L110="","",IF(L110=K110,"Có","Không"))
A111: 110 | B111: C | C111: ViBIRD | D111: Qwen2.5-Coder-7B / full | E111: Hãy cho biết chặng đua và năm của chặng đua mà Michael Schumacher có vòng đua nhanh nhất. | F111: vòng đua nhanh nhất tham chiếu tới min(milliseconds); Alex Yoong tham chiếu đến tên đầy đủ của người lái; tên đầy đủ của người lái tham chiếu tới drivers.forename và drivers.surname; | G111: Table: driverStandings (Lịch Sử Kết Quả Đua Xe) - driverStandingsId INTEGER | alias: Mã Lịch Sử Kết Quả, ID Lịch Sử Kết Quả, Mã Kết Quả | values: 1, 2, 3 | -- Mã duy nhất để xác định mỗi dòng lịch sử kết quả. - raceId INTEGER | alias: Mã Giải Đua, ID Giải Đua, Mã Giải | values: 18, 19, 20 | -- Mã duy nhất để xác định mỗi giải đua. - driverId INTEGER | alias: Mã Tài Xế, ID Tài Xế, Mã Tài | values: 1, 2, 3 | -- Mã duy nhất để xác định mỗi tài xế. - position INTEGER | alias: Vị Trí, Thứ Tự, Vị Trí Đua | values: 1, 2, 3 | -- Vị trí của tài xế trong cuộc đua. Table: lapTimes (Kết Quả Tròn) - raceId INTEGER | alias: ID Giải Đấu, Mã Giải Đấu, Số Giải Đấu | values: 2, 3, 4 | -- Mã duy nhất xác định giải đấu. - driverId INTEGER | alias: ID Tài Xế, Mã Tài Xế, Số Tài Xế | values: 1, 2, 3 | -- Mã duy nhất xác định tài xế trong giải đấu. - lap INTEGER | alias: Tròn, Lần Quanh, Tròn Đường | values: 1, 2, 3 | -- Số tròn đua mà tài xế đã hoàn thành. Table: qualifying (Kết quả bấm nút) - qualifyId INTEGER | alias: Mã vòng bấm nút, Mã vòng đua, ID vòng bấm nút | values: 23, 24, 25 | -- Mã duy nhất xác định mỗi vòng bấm nút. - raceId INTEGER | alias: Mã cuộc đua, ID cuộc đua, Mã giải đấu | values: 19, 20, 21 | -- Mã duy nhất xác định mỗi cuộc đua. - driverId INTEGER | alias: Mã tài xế, ID tài xế, Mã lái xe | values: 13, 8, 5 | -- Mã duy nhất xác định mỗi tài xế tham gia cuộc đua. - constructorId INTEGER | alias: Mã đội đua, ID đội đua, Mã nhà sản xuất | values: 6, 1, 7 | -- Mã duy nhất xác định mỗi đội đua tham gia cuộc đua. - q1 TEXT | alias: Thời gian vòng 1, Thời gian vòng đầu tiên, Thời gian vòng 1 | values: 1:35.347, 1:35.645, 1:35.227 | -- Thời gian bấm nút nhanh nhất trong vòng 1. - q2 TEXT | alias: Thời gian vòng 2, Thời gian vòng thứ hai, Thời gian vòng 2 | values: 1:34.412, 1:34.188, 1:34.759 | -- Thời gian bấm nút nhanh nhất trong vòng 2. - q3 TEXT | alias: Thời gian vòng 3, Thời gian vòng cuối cùng, Thời gian vòng 3 | values: 1:35.748, 1:36.230, 1:36.613 | -- Thời gian bấm nút nhanh nhất trong vòng 3. Table: races (Giải đua xe ô tô) - raceId INTEGER | alias: Mã giải đua, ID giải đua, Số giải đua | values: 837, 833, 838 | -- Mã duy nhất xác định mỗi cuộc đua. - year INTEGER | alias: Năm, Nam, Năm tổ chức | values: 2009, 2008, 2007 | -- Năm mà cuộc đua được tổ chức. - round INTEGER | alias: Vòng đua, Vòng, Số vòng | values: 2, 3, 4 | -- Vị trí của cuộc đua trong mùa giải. - circuitId INTEGER | alias: Mã đường đua, ID đường đua, Số đường đua | values: 2, 17, 3 | -- Mã duy nhất xác định mỗi đường đua. Table: results (Kết quả đua) - resultId INTEGER | alias: Mã kết quả, ID kết quả, Mã đua | values: 23, 24, 25 | -- Mã duy nhất để xác định mỗi kết quả đua. - raceId INTEGER | alias: Mã giải đua, ID giải đua, Số giải đua | values: 19, 20, 21 | -- Mã duy nhất để xác định mỗi giải đua. - driverId INTEGER | alias: Mã tài xế, ID tài xế, Số tài xế | values: 8, 9, 5 | -- Mã duy nhất để xác định mỗi tài xế tham gia đua. - constructorId INTEGER | alias: Mã đội đua, ID đội đua, Số đội đua | values: 6, 2, 1 | -- Mã duy nhất để xác định mỗi đội đua. - laps INTEGER | alias: Laps, Lộ trình, Lần đi quanh | values: 56, 55, 54 | -- Số vòng đua mà tài xế đã hoàn thành. - fastestLap INTEGER | alias: Quãng đường nhanh nhất, Quãng đường tốt nhất, Quãng đường nhanh | values: 37, 39, 19 | -- Số vòng đua trong quãng đường nhanh nhất của lái xe. - fastestLapTime TEXT | alias: Thời gian quãng đường nhanh nhất, Thời gian tốt nhất, Thời gian nhanh nhất | values: 1:35.405, 1:35.921, 1:35.922 | -- Thời gian hoàn thành quãng đường nhanh nhất của lái xe. - fastestLapSpeed TEXT | alias: Tốc độ trung bình quãng đường nhanh nhất, Tốc độ nhanh nhất, Tốc độ tốt nhất | values: 209.158, 208.033, 208.031 | -- Tốc độ trung bình khi lái xe hoàn thành quãng đường nhanh nhất. - statusId INTEGER | alias: Trạng thái, Trạng thái lái xe, Trạng thái cuộc đua | values: 1, 11, 12 | -- Mã trạng thái của lái xe tại thời điểm kết thúc cuộc đua. Foreign keys: driverStandings.raceId = races.raceId driverStandings.driverId = drivers.driverId lapTimes.raceId = races.raceId lapTimes.driverId = drivers.driverId qualifying.raceId = races.raceId qualifying.driverId = drivers.driverId qualifying.constructorId = constructors.constructorId races.year = seasons.year races.circuitId = circuits.circuitId results.raceId = races.raceId results.driverId = drivers.driverId results.constructorId = constructors.constructorId results.statusId = status.statusId | H111: SELECT c.name AS CircuitName, r.year AS Year FROM results res JOIN drivers d ON res.driverid = d.driverid JOIN races r ON res.raceid = r.raceid JOIN circuits c ON r.circuitid = c.circuitid WHERE d.forename = 'Michael' AND d.surname = 'Schumacher' ORDER BY CAST(REPLACE(SUBSTR(res.fastestlapspeed, 4), ',', '') AS REAL) DESC LIMIT 1; | I111: SELECT T1.name, T1.year FROM races AS T1 INNER JOIN lapTimes AS T2 ON T2.raceId = T1.raceId INNER JOIN drivers AS T3 ON T3.driverId = T2.driverId WHERE T3.forename = 'Michael' AND T3.surname = 'Schumacher' ORDER BY T2.milliseconds ASC LIMIT 1 | J111: ok | K111: Thiếu bảng cần thiết trong schema | M111: =IF(L111="","",IF(L111=K111,"Có","Không"))
A112: 111 | B112: C | C112: ViBIRD | D112: Qwen2.5-Coder-7B / full | E112: Trong chặng đua F1 nào, Lewis Hamilton có hạng cao nhất? | F112: hạng cao nhất tương ứng với min(rank); Lewis Hamilton là tên đầy đủ của người lái xe; tên đầy đủ của người lái xe tương ứng với drivers.forename và drivers.surname; | G112: Table: driverStandings (Lịch Sử Kết Quả Đua Xe) - driverStandingsId INTEGER | alias: Mã Lịch Sử Kết Quả, ID Lịch Sử Kết Quả, Mã Kết Quả | values: 1, 2, 3 | -- Mã duy nhất để xác định mỗi dòng lịch sử kết quả. - raceId INTEGER | alias: Mã Giải Đua, ID Giải Đua, Mã Giải | values: 18, 19, 20 | -- Mã duy nhất để xác định mỗi giải đua. - driverId INTEGER | alias: Mã Tài Xế, ID Tài Xế, Mã Tài | values: 1, 2, 3 | -- Mã duy nhất để xác định mỗi tài xế. - points REAL | alias: Số Điểm, Điểm, Điểm Số | values: 10.0, 8.0, 6.0 | -- Số điểm mà tài xế đã giành được sau mỗi cuộc đua. - position INTEGER | alias: Vị Trí, Thứ Tự, Vị Trí Đua | values: 1, 2, 3 | -- Vị trí của tài xế trong cuộc đua. - positionText TEXT | alias: Vị Trí Văn Bản, Thứ Tự Văn Bản, Vị Trí Đua Văn Bản | values: 1, 2, 3 | -- Biểu diễn văn bản của vị trí của tài xế trong cuộc đua. Table: lapTimes (Kết Quả Tròn) - raceId INTEGER | alias: ID Giải Đấu, Mã Giải Đấu, Số Giải Đấu | values: 2, 3, 4 | -- Mã duy nhất xác định giải đấu. - driverId INTEGER | alias: ID Tài Xế, Mã Tài Xế, Số Tài Xế | values: 1, 2, 3 | -- Mã duy nhất xác định tài xế trong giải đấu. - lap INTEGER | alias: Tròn, Lần Quanh, Tròn Đường | values: 1, 2, 3 | -- Số tròn đua mà tài xế đã hoàn thành. - position INTEGER | alias: Vị Trí, Hạng Đứng, Vị Trí Đua | values: 10, 11, 9 | -- Vị trí của tài xế sau khi hoàn thành tròn đua. Table: qualifying (Kết quả bấm nút) - qualifyId INTEGER | alias: Mã vòng bấm nút, Mã vòng đua, ID vòng bấm nút | values: 23, 24, 25 | -- Mã duy nhất xác định mỗi vòng bấm nút. - raceId INTEGER | alias: Mã cuộc đua, ID cuộc đua, Mã giải đấu | values: 19, 20, 21 | -- Mã duy nhất xác định mỗi cuộc đua. - driverId INTEGER | alias: Mã tài xế, ID tài xế, Mã lái xe | values: 13, 8, 5 | -- Mã duy nhất xác định mỗi tài xế tham gia cuộc đua. - constructorId INTEGER | alias: Mã đội đua, ID đội đua, Mã nhà sản xuất | values: 6, 1, 7 | -- Mã duy nhất xác định mỗi đội đua tham gia cuộc đua. - position INTEGER | alias: Vị trí, Hạng vị, Số thứ tự | values: 1, 2, 3 | -- Vị trí của tài xế trong vòng bấm nút. Table: results (Kết quả đua) - resultId INTEGER | alias: Mã kết quả, ID kết quả, Mã đua | values: 23, 24, 25 | -- Mã duy nhất để xác định mỗi kết quả đua. - raceId INTEGER | alias: Mã giải đua, ID giải đua, Số giải đua | values: 19, 20, 21 | -- Mã duy nhất để xác định mỗi giải đua. - driverId INTEGER | alias: Mã tài xế, ID tài xế, Số tài xế | values: 8, 9, 5 | -- Mã duy nhất để xác định mỗi tài xế tham gia đua. - constructorId INTEGER | alias: Mã đội đua, ID đội đua, Số đội đua | values: 6, 2, 1 | -- Mã duy nhất để xác định mỗi đội đua. - position INTEGER | alias: Vị trí, Hạng vị, Vị trí chấm dứt | values: 1, 2, 3 | -- Vị trí của tài xế khi kết thúc cuộc đua. - laps INTEGER | alias: Laps, Lộ trình, Lần đi quanh | values: 56, 55, 54 | -- Số vòng đua mà tài xế đã hoàn thành. - fastestLap INTEGER | alias: Quãng đường nhanh nhất, Quãng đường tốt nhất, Quãng đường nhanh | values: 37, 39, 19 | -- Số vòng đua trong quãng đường nhanh nhất của lái xe. - rank INTEGER | alias: Hạng, Số hạng, Hạng mục | values: 2, 6, 7 | -- Hạng của lái xe sau khi kết thúc cuộc đua. - statusId INTEGER | alias: Trạng thái, Trạng thái lái xe, Trạng thái cuộc đua | values: 1, 11, 12 | -- Mã trạng thái của lái xe tại thời điểm kết thúc cuộc đua. Foreign keys: driverStandings.raceId = races.raceId driverStandings.driverId = drivers.driverId lapTimes.raceId = races.raceId lapTimes.driverId = drivers.driverId qualifying.raceId = races.raceId qualifying.driverId = drivers.driverId qualifying.constructorId = constructors.constructorId results.raceId = races.raceId results.driverId = drivers.driverId results.constructorId = constructors.constructorId results.statusId = status.statusId | H112: SELECT r.round, r.name FROM races r JOIN results res ON r.raceid = res.raceid JOIN drivers d ON res.driverid = d.driverid WHERE d.forename = 'Lewis' AND d.surname = 'Hamilton' ORDER BY res.rank ASC LIMIT 1; | I112: SELECT name FROM races WHERE raceId IN ( SELECT raceId FROM results WHERE rank = 1 AND driverId = ( SELECT driverId FROM drivers WHERE forename = 'Lewis' AND surname = 'Hamilton' ) ) | J112: ok | K112: Thiếu bảng cần thiết trong schema | M112: =IF(L112="","",IF(L112=K112,"Có","Không"))
A113: 112 | B113: C | C113: ViBIRD | D113: Qwen2.5-Coder-7B / full | E113: Liệt kê ID của các tay đua đứng trong top năm, theo thứ tự giảm dần về thời gian nhanh nhất trong vòng đầu tiên của cuộc đua. | F113: thời gian nhanh nhất tham chiếu tới Min(time); | G113: Table: constructorStandings (Bảng Xếp Hạng Constructors) - constructorStandingsId INTEGER | alias: ID Xếp Hạng Constructor, Mã Xếp Hạng Constructor, ID Constructor | values: 1, 2, 3 | -- Mã duy nhất để xác định mỗi dòng trong bảng xếp hạng constructor. - raceId INTEGER | alias: ID Giải Đua, Mã Giải Đua, ID Giải | values: 18, 19, 20 | -- Mã duy nhất để xác định mỗi giải đua trong bảng xếp hạng. - constructorId INTEGER | alias: ID Constructor, Mã Constructor, ID Xe | values: 1, 2, 3 | -- Mã duy nhất để xác định mỗi đội đua trong bảng xếp hạng. Table: driverStandings (Lịch Sử Kết Quả Đua Xe) - driverStandingsId INTEGER | alias: Mã Lịch Sử Kết Quả, ID Lịch Sử Kết Quả, Mã Kết Quả | values: 1, 2, 3 | -- Mã duy nhất để xác định mỗi dòng lịch sử kết quả. - raceId INTEGER | alias: Mã Giải Đua, ID Giải Đua, Mã Giải | values: 18, 19, 20 | -- Mã duy nhất để xác định mỗi giải đua. - driverId INTEGER | alias: Mã Tài Xế, ID Tài Xế, Mã Tài | values: 1, 2, 3 | -- Mã duy nhất để xác định mỗi tài xế. Table: drivers (Hãnh trang đua xe) - driverId INTEGER | alias: Mã tài xế, ID tài xế, Số tài xế | values: 452, 625, 103 | -- Mã duy nhất xác định mỗi tài xế trong bảng. Table: lapTimes (Kết Quả Tròn) - raceId INTEGER | alias: ID Giải Đấu, Mã Giải Đấu, Số Giải Đấu | values: 2, 3, 4 | -- Mã duy nhất xác định giải đấu. - driverId INTEGER | alias: ID Tài Xế, Mã Tài Xế, Số Tài Xế | values: 1, 2, 3 | -- Mã duy nhất xác định tài xế trong giải đấu. - lap INTEGER | alias: Tròn, Lần Quanh, Tròn Đường | values: 1, 2, 3 | -- Số tròn đua mà tài xế đã hoàn thành. Table: qualifying (Kết quả bấm nút) - qualifyId INTEGER | alias: Mã vòng bấm nút, Mã vòng đua, ID vòng bấm nút | values: 23, 24, 25 | -- Mã duy nhất xác định mỗi vòng bấm nút. - raceId INTEGER | alias: Mã cuộc đua, ID cuộc đua, Mã giải đấu | values: 19, 20, 21 | -- Mã duy nhất xác định mỗi cuộc đua. - driverId INTEGER | alias: Mã tài xế, ID tài xế, Mã lái xe | values: 13, 8, 5 | -- Mã duy nhất xác định mỗi tài xế tham gia cuộc đua. - constructorId INTEGER | alias: Mã đội đua, ID đội đua, Mã nhà sản xuất | values: 6, 1, 7 | -- Mã duy nhất xác định mỗi đội đua tham gia cuộc đua. Table: results (Kết quả đua) - resultId INTEGER | alias: Mã kết quả, ID kết quả, Mã đua | values: 23, 24, 25 | -- Mã duy nhất để xác định mỗi kết quả đua. - raceId INTEGER | alias: Mã giải đua, ID giải đua, Số giải đua | values: 19, 20, 21 | -- Mã duy nhất để xác định mỗi giải đua. - driverId INTEGER | alias: Mã tài xế, ID tài xế, Số tài xế | values: 8, 9, 5 | -- Mã duy nhất để xác định mỗi tài xế tham gia đua. - constructorId INTEGER | alias: Mã đội đua, ID đội đua, Số đội đua | values: 6, 2, 1 | -- Mã duy nhất để xác định mỗi đội đua. - statusId INTEGER | alias: Trạng thái, Trạng thái lái xe, Trạng thái cuộc đua | values: 1, 11, 12 | -- Mã trạng thái của lái xe tại thời điểm kết thúc cuộc đua. Foreign keys: constructorStandings.raceId = races.raceId constructorStandings.constructorId = constructors.constructorId driverStandings.raceId = races.raceId driverStandings.driverId = drivers.driverId lapTimes.raceId = races.raceId lapTimes.driverId = drivers.driverId qualifying.raceId = races.raceId qualifying.driverId = drivers.driverId qualifying.constructorId = constructors.constructorId results.raceId = races.raceId results.driverId = drivers.driverId results.constructorId = constructors.constructorId results.statusId = status.statusId | H113: SELECT driverId FROM lapTimes WHERE raceId = 1 ORDER BY time ASC LIMIT 5; | I113: SELECT driverId FROM lapTimes WHERE lap = 1 ORDER BY time LIMIT 5 | J113: ok | K113: Sai cột | M113: =IF(L113="","",IF(L113=K113,"Có","Không"))
... A121: 120 | B121: C | C121: ViBIRD | D121: Qwen2.5-Coder-7B / full | E121: Chi tiêu hàng tháng lớn nhất của những khách hàng sử dụng euro là bao nhiêu? | F121: Chi tiêu hàng tháng = SUM(consumption) / 12 | G121: Table: customers (Khách hàng) - CustomerID INTEGER | alias: Mã khách hàng, ID khách hàng, Số khách hàng | values: 3, 5, 6 | -- Mã duy nhất xác định mỗi khách hàng - Segment TEXT | alias: Phân khúc, Nhóm khách hàng, Loại khách hàng | values: SME, LAM, KAM | -- Phân loại khách hàng dựa trên đặc điểm kinh doanh - Currency TEXT | alias: Đơn vị tiền tệ, Tiền tệ, ĐVT tiền tệ | values: EUR, CZK | -- Loại tiền tệ được sử dụng trong giao dịch với khách hàng Table: transactions_1k (Giao_dịch_1000) - TransactionID INTEGER | alias: Mã_giao_dịch, Mã giao dịch, ID giao dịch | values: 1, 2, 3 | -- Mã duy nhất để xác định mỗi giao dịch - CustomerID INTEGER | alias: Mã_khách_hàng, Mã khách, ID khách hàng | values: 31543, 46707, 7654 | -- Mã duy nhất để xác định mỗi khách hàng - CardID INTEGER | alias: Mã_thẻ, Mã thẻ tín dụng, Mã thẻ ghi nợ | values: 486621, 550134, 684220 | -- Mã thẻ được sử dụng trong giao dịch - ProductID INTEGER | alias: Mã_sản_phẩm, Mã sản phẩm, ID sản phẩm | values: 2, 23, 5 | -- Mã sản phẩm được mua trong giao dịch - Amount INTEGER | alias: Số_lượng, Số lượng mua, Số lượng sản phẩm | values: 28, 18, 1 | -- Số lượng sản phẩm được mua trong giao dịch - Price REAL | alias: Giá, Giá tiền, Giá bán | values: 672.64, 430.72, 121.99 | -- Giá của sản phẩm trong giao dịch Table: yearmonth (Tháng_Năm) - CustomerID INTEGER | alias: MãKháchHàng, IDKháchHàng, KHID | values: 39, 63, 172 | -- Mã duy nhất xác định khách hàng trong hệ thống. - Date TEXT | alias: NgàyTháng, ThángNăm, Thời Gian | values: 201112, 201201, 201202 | -- Ký hiệu năm tháng (ví dụ: 201112 cho tháng 12 năm 2011). - Consumption REAL | alias: SửDụng, Tiêu thụ, Dùng | values: 528.3, 1598.28, 1931.36 | -- Số lượng tiêu thụ hoặc sử dụng trong đơn vị đo lường tương ứng. Foreign keys: yearmonth.CustomerID = customers.None | H121: SELECT AVG(T2.Consumption) AS MonthlySpending FROM customers AS T1 JOIN yearmonth AS T2 ON T1.CustomerID = T2.CustomerID WHERE T1.Currency = 'EUR' GROUP BY T1.CustomerID ORDER BY MonthlySpending DESC LIMIT 1; | I121: SELECT SUM(T2.Consumption) / 12 AS MonthlyConsumption FROM customers AS T1 INNER JOIN yearmonth AS T2 ON T1.CustomerID = T2.CustomerID WHERE T1.Currency = 'EUR' GROUP BY T1.CustomerID ORDER BY MonthlyConsumption DESC LIMIT 1 | J121: ok | K121: Sai cột | M121: =IF(L121="","",IF(L121=K121,"Có","Không"))

Sheet Tổng hợp
A1: Chỉ số | B1: Giá trị
A2: Số dòng đã chấm | B2: =COUNTA('Lỗi'!L2:L121)
A3: Tỉ lệ nhãn tự động đúng | B3: =IF(B2=0,"",COUNTIF('Lỗi'!M2:M121,"Có")/B2)
A4: Số câu đề xuất làm ví dụ | B4: =COUNTIF('Lỗi'!O2:O121,"Có")
A5: Số câu hỏi/SQL tham chiếu có vấn đề | B5: =COUNTIF('Lỗi'!N2:N121,"Có")
A7: Nhãn | B7: Nhãn tự động | C7: Nhãn người chấm
A8: SQL không chạy được | B8: =COUNTIF('Lỗi'!K2:K121,A8) | C8: =COUNTIF('Lỗi'!L2:L121,A8)
A9: Thiếu bảng cần thiết trong schema | B9: =COUNTIF('Lỗi'!K2:K121,A9) | C9: =COUNTIF('Lỗi'!L2:L121,A9)
A10: Chọn sai bảng | B10: =COUNTIF('Lỗi'!K2:K121,A10) | C10: =COUNTIF('Lỗi'!L2:L121,A10)
A11: Sai cột | B11: =COUNTIF('Lỗi'!K2:K121,A11) | C11: =COUNTIF('Lỗi'!L2:L121,A11)
A12: Sai hàm gộp hoặc GROUP BY | B12: =COUNTIF('Lỗi'!K2:K121,A12) | C12: =COUNTIF('Lỗi'!L2:L121,A12)
A13: Sai điều kiện hoặc giá trị | B13: =COUNTIF('Lỗi'!K2:K121,A13) | C13: =COUNTIF('Lỗi'!L2:L121,A13)
A14: Sai sắp xếp hoặc LIMIT | B14: =COUNTIF('Lỗi'!K2:K121,A14) | C14: =COUNTIF('Lỗi'!L2:L121,A14)
A15: Khác | B15: =COUNTIF('Lỗi'!K2:K121,A15) | C15: =COUNTIF('Lỗi'!L2:L121,A15)

Sheet Danh mục
A1: Nhãn lỗi | B1: Có/Không
A2: SQL không chạy được | B2: Có
A3: Thiếu bảng cần thiết trong schema | B3: Không
A4: Chọn sai bảng
A5: Sai cột
A6: Sai hàm gộp hoặc GROUP BY
A7: Sai điều kiện hoặc giá trị
A8: Sai sắp xếp hoặc LIMIT
A9: Khác
